[{"id":"a06db5d4-9549-48ce-8337-82b24023ac29","index":14,"period":1,"minute":0,"second":4,"timestamp":"00:00:04.404","team":"Bolivia","player":"Boris Cespedes","type":"Pressure","location":[51.7,41.8],"endLocation":null,"outcome":null,"possession":2,"xg":null},{"id":"9f4f5fe7-dd15-462d-b2eb-c66420f6fa5e","index":18,"period":1,"minute":0,"second":7,"timestamp":"00:00:07.613","team":"Bolivia","player":"José Manuel Sagredo Chávez","type":"Pressure","location":[14.7,11.3],"endLocation":null,"outcome":null,"possession":2,"xg":null},{"id":"8dc4102d-9b40-489a-91ae-e98854b03d75","index":21,"period":1,"minute":0,"second":9,"timestamp":"00:00:09.256","team":"Bolivia","player":"Ramiro Vaca Ponce","type":"Pressure","location":[22,7.2],"endLocation":null,"outcome":null,"possession":2,"xg":null},{"id":"336c617f-2478-4ba3-aaa3-3a3debb3f28f","index":24,"period":1,"minute":0,"second":10,"timestamp":"00:00:10.099","team":"Bolivia","player":"José Manuel Sagredo Chávez","type":"Pressure","location":[19.7,5],"endLocation":null,"outcome":null,"possession":2,"xg":null},{"id":"7550244e-273c-46b3-80d8-7ab6ba4df2a2","index":45,"period":1,"minute":0,"second":41,"timestamp":"00:00:41.731","team":"Bolivia","player":"Carmelo Algarañaz Añez","type":"Pressure","location":[99.6,38],"endLocation":null,"outcome":null,"possession":3,"xg":null},{"id":"80c40c7b-b38b-4a23-861f-46cbab8ebf6a","index":48,"period":1,"minute":0,"second":59,"timestamp":"00:00:59.154","team":"Panama","player":"Michael Amir Murillo Bermudez","type":"Pressure","location":[50.6,66.9],"endLocation":null,"outcome":null,"possession":4,"xg":null},{"id":"a876c116-19fc-4629-8d64-49aeca2d98e9","index":51,"period":1,"minute":1,"second":0,"timestamp":"00:01:00.539","team":"Panama","player":"César Rodolfo Blackman Camarena","type":"Pressure","location":[57.2,74.9],"endLocation":null,"outcome":null,"possession":4,"xg":null},{"id":"114c266e-7e27-4a1e-8198-c6bd97d7a5ac","index":56,"period":1,"minute":1,"second":3,"timestamp":"00:01:03.166","team":"Panama","player":"José Fajardo Nelson","type":"Pressure","location":[75.5,71.6],"endLocation":null,"outcome":null,"possession":4,"xg":null},{"id":"aff1d182-9f95-45c8-bb7e-5109c3ac01e2","index":69,"period":1,"minute":1,"second":15,"timestamp":"00:01:15.338","team":"Panama","player":"Edgar Yoel Bárcenas Herrera","type":"Pressure","location":[83.9,6.6],"endLocation":null,"outcome":null,"possession":4,"xg":null},{"id":"f0525337-0b78-43f2-b7c5-90285917a608","index":73,"period":1,"minute":1,"second":16,"timestamp":"00:01:16.861","team":"Panama","player":"José Fajardo Nelson","type":"Pressure","location":[92.5,19.8],"endLocation":null,"outcome":null,"possession":4,"xg":null},{"id":"b7c797cb-4d9e-4257-824c-a88cb8fa5c14","index":75,"period":1,"minute":1,"second":19,"timestamp":"00:01:19.195","team":"Panama","player":"José Fajardo Nelson","type":"Pressure","location":[105,29.5],"endLocation":null,"outcome":null,"possession":4,"xg":null},{"id":"dc10ad9a-793b-40be-9d92-0df57db7380c","index":84,"period":1,"minute":1,"second":36,"timestamp":"00:01:36.910","team":"Bolivia","player":"Carmelo Algarañaz Añez","type":"Pressure","location":[110.6,46],"endLocation":null,"outcome":null,"possession":5,"xg":null},{"id":"94dbe458-e448-49b3-b4dd-6b667c43f978","index":90,"period":1,"minute":1,"second":47,"timestamp":"00:01:47.038","team":"Bolivia","player":"Miguel Ángel Terceros","type":"Pressure","location":[85.6,71.3],"endLocation":null,"outcome":null,"possession":5,"xg":null},{"id":"9c63b629-5c96-42e5-a5fe-a2f933fafcf7","index":94,"period":1,"minute":1,"second":50,"timestamp":"00:01:50.001","team":"Bolivia","player":"Héctor Manuel Cuellar Rosales","type":"Pressure","location":[44.9,76.8],"endLocation":null,"outcome":null,"possession":5,"xg":null},{"id":"655c5761-1417-4a6d-b901-d03128963c7b","index":98,"period":1,"minute":1,"second":52,"timestamp":"00:01:52.098","team":"Bolivia","player":"Yomar Rene Rocha Rodriguez","type":"Pressure","location":[49.6,74],"endLocation":null,"outcome":null,"possession":5,"xg":null},{"id":"944652e6-0a1b-475f-bad5-0bd5c555c3e3","index":102,"period":1,"minute":1,"second":53,"timestamp":"00:01:53.647","team":"Bolivia","player":"Yomar Rene Rocha Rodriguez","type":"Pressure","location":[46.3,65.2],"endLocation":null,"outcome":null,"possession":5,"xg":null},{"id":"a05b2afb-a96e-43c5-967c-5a676c4a15db","index":103,"period":1,"minute":1,"second":54,"timestamp":"00:01:54.405","team":"Bolivia","player":"Héctor Manuel Cuellar Rosales","type":"Pressure","location":[40.4,64.2],"endLocation":null,"outcome":null,"possession":5,"xg":null},{"id":"7d70ca8b-ca12-49a0-a236-d857483afa0f","index":112,"period":1,"minute":2,"second":17,"timestamp":"00:02:17.733","team":"Panama","player":"José Ángel Córdoba Chambers","type":"Pressure","location":[38.5,7.8],"endLocation":null,"outcome":null,"possession":6,"xg":null},{"id":"cb005826-1e31-49b8-9c1e-04723491e2d7","index":117,"period":1,"minute":2,"second":19,"timestamp":"00:02:19.774","team":"Bolivia","player":"Carmelo Algarañaz Añez","type":"Pressure","location":[77.8,74.7],"endLocation":null,"outcome":null,"possession":7,"xg":null},{"id":"d741b433-6930-48f0-8b42-34cf883552ce","index":147,"period":1,"minute":2,"second":51,"timestamp":"00:02:51.917","team":"Panama","player":"César Rodolfo Blackman Camarena","type":"Pressure","location":[104.3,11.6],"endLocation":null,"outcome":null,"possession":8,"xg":null},{"id":"3ec90e88-0ba4-421e-96ee-6f4e90ffeae6","index":155,"period":1,"minute":3,"second":0,"timestamp":"00:03:00.064","team":"Bolivia","player":"Héctor Manuel Cuellar Rosales","type":"Pressure","location":[17,61.4],"endLocation":null,"outcome":null,"possession":9,"xg":null},{"id":"43ad05e1-9ce5-4eb4-a6a7-a4b560b24882","index":168,"period":1,"minute":3,"second":10,"timestamp":"00:03:10.667","team":"Panama","player":"José Fajardo Nelson","type":"Pressure","location":[91.3,51.5],"endLocation":null,"outcome":null,"possession":9,"xg":null},{"id":"381a829b-3841-4509-acac-50af73481483","index":176,"period":1,"minute":3,"second":14,"timestamp":"00:03:14.977","team":"Panama","player":"Jovani Francisco Welch Lopez","type":"Pressure","location":[85.6,29.3],"endLocation":null,"outcome":null,"possession":10,"xg":null},{"id":"9b69d58c-5ecc-47d2-8126-7a9d2a8902ef","index":184,"period":1,"minute":3,"second":20,"timestamp":"00:03:20.413","team":"Bolivia","player":"Miguel Ángel Terceros","type":"Pressure","location":[52.5,74],"endLocation":null,"outcome":null,"possession":10,"xg":null},{"id":"717acdd2-0e99-4473-a12b-6d811f99d063","index":186,"period":1,"minute":3,"second":21,"timestamp":"00:03:21.910","team":"Bolivia","player":"Yomar Rene Rocha Rodriguez","type":"Pressure","location":[37.3,76.5],"endLocation":null,"outcome":null,"possession":10,"xg":null},{"id":"895220f8-4d53-4a03-8fa9-feab9719cf74","index":198,"period":1,"minute":3,"second":30,"timestamp":"00:03:30.905","team":"Panama","player":"Edgardo Isaac Fariña Wynter","type":"Pressure","location":[72.4,31.4],"endLocation":null,"outcome":null,"possession":10,"xg":null},{"id":"e0261403-c447-4c25-b1e2-2a7abd3234ce","index":222,"period":1,"minute":4,"second":34,"timestamp":"00:04:34.420","team":"Panama","player":"Edgar Yoel Bárcenas Herrera","type":"Pressure","location":[90.6,57.4],"endLocation":null,"outcome":null,"possession":12,"xg":null},{"id":"8f2fb090-e86b-4750-aacc-9a4e1b65f127","index":227,"period":1,"minute":4,"second":39,"timestamp":"00:04:39.773","team":"Panama","player":"José Fajardo Nelson","type":"Pressure","location":[80.1,36.4],"endLocation":null,"outcome":null,"possession":12,"xg":null},{"id":"5511c979-0ea5-4515-ae81-e9cc2afc0b37","index":246,"period":1,"minute":5,"second":1,"timestamp":"00:05:01.290","team":"Bolivia","player":"Ramiro Vaca Ponce","type":"Pressure","location":[95.8,7],"endLocation":null,"outcome":null,"possession":13,"xg":null},{"id":"4630df2e-de8f-406a-87a5-e4dbd54e19d5","index":250,"period":1,"minute":5,"second":14,"timestamp":"00:05:14.306","team":"Bolivia","player":"Luis Fernando Haquín Lopez","type":"Pressure","location":[65.2,28.3],"endLocation":null,"outcome":null,"possession":14,"xg":null},{"id":"ed95ebd0-c8a5-4501-8bb4-795bb152edf4","index":270,"period":1,"minute":5,"second":48,"timestamp":"00:05:48.075","team":"Bolivia","player":"Héctor Manuel Cuellar Rosales","type":"Pressure","location":[48.5,65.5],"endLocation":null,"outcome":null,"possession":15,"xg":null},{"id":"1ccd988b-fde4-41a9-b19e-a7a54cd45ac1","index":288,"period":1,"minute":6,"second":7,"timestamp":"00:06:07.849","team":"Bolivia","player":"José Manuel Sagredo Chávez","type":"Pressure","location":[57,6.3],"endLocation":null,"outcome":null,"possession":15,"xg":null},{"id":"7831fabf-52fc-43cb-949f-b71b3bf50b6a","index":298,"period":1,"minute":6,"second":48,"timestamp":"00:06:48.017","team":"Bolivia","player":"Luis Fernando Haquín Lopez","type":"Pressure","location":[48.7,53.9],"endLocation":null,"outcome":null,"possession":17,"xg":null},{"id":"9905dd1a-e5ed-4235-91a0-5f4e299de2b7","index":302,"period":1,"minute":6,"second":51,"timestamp":"00:06:51.309","team":"Bolivia","player":"Luis Fernando Haquín Lopez","type":"Pressure","location":[35.2,48.9],"endLocation":null,"outcome":null,"possession":17,"xg":null},{"id":"7f326955-2771-49be-a073-b0a9200e6f39","index":306,"period":1,"minute":6,"second":57,"timestamp":"00:06:57.083","team":"Bolivia","player":"Marcelo Sebastián Suárez Justiniano","type":"Pressure","location":[19.9,28.8],"endLocation":null,"outcome":null,"possession":17,"xg":null},{"id":"5d3992ac-7f2c-49f4-9648-e5835f31adc0","index":310,"period":1,"minute":7,"second":0,"timestamp":"00:07:00.425","team":"Bolivia","player":"José Manuel Sagredo Chávez","type":"Pressure","location":[11.6,17.2],"endLocation":null,"outcome":null,"possession":17,"xg":null},{"id":"3e61e664-84a4-4437-acce-74733aff910b","index":330,"period":1,"minute":7,"second":16,"timestamp":"00:07:16.747","team":"Bolivia","player":"Boris Cespedes","type":"Pressure","location":[46.6,56.4],"endLocation":null,"outcome":null,"possession":17,"xg":null},{"id":"a7cbb9b9-437a-4d2e-a793-09c13d90e7ed","index":348,"period":1,"minute":7,"second":27,"timestamp":"00:07:27.662","team":"Bolivia","player":"Yomar Rene Rocha Rodriguez","type":"Pressure","location":[50.6,61.2],"endLocation":null,"outcome":null,"possession":17,"xg":null},{"id":"db474e28-047d-4100-92e4-fa4737ec5664","index":369,"period":1,"minute":8,"second":31,"timestamp":"00:08:31.891","team":"Bolivia","player":"Boris Cespedes","type":"Pressure","location":[59.5,48.4],"endLocation":null,"outcome":null,"possession":20,"xg":null},{"id":"ad5e230c-7290-4536-a265-5fa6e3ce4e43","index":382,"period":1,"minute":8,"second":44,"timestamp":"00:08:44.634","team":"Bolivia","player":"José Manuel Sagredo Chávez","type":"Pressure","location":[81.3,5.2],"endLocation":null,"outcome":null,"possession":20,"xg":null},{"id":"0e669d5a-8384-4c1a-b004-5d3dd07456af","index":385,"period":1,"minute":8,"second":46,"timestamp":"00:08:46.427","team":"Panama","player":"Cristian Jesús Martínez","type":"Pressure","location":[41.9,60.6],"endLocation":null,"outcome":null,"possession":20,"xg":null},{"id":"e0d6c0cf-99a3-4af7-b26e-f4d3c3b9d09f","index":387,"period":1,"minute":8,"second":47,"timestamp":"00:08:47.724","team":"Panama","player":"José Ángel Córdoba Chambers","type":"Pressure","location":[30.5,43],"endLocation":null,"outcome":null,"possession":20,"xg":null},{"id":"a250508e-9173-4a77-a016-3821ea2db161","index":398,"period":1,"minute":8,"second":59,"timestamp":"00:08:59.681","team":"Bolivia","player":"Boris Cespedes","type":"Pressure","location":[54.8,62.9],"endLocation":null,"outcome":null,"possession":20,"xg":null},{"id":"b7d2f6a6-e683-4416-8908-f1ccca721f7f","index":416,"period":1,"minute":9,"second":13,"timestamp":"00:09:13.158","team":"Bolivia","player":"Luis Fernando Haquín Lopez","type":"Pressure","location":[38.7,64],"endLocation":null,"outcome":null,"possession":20,"xg":null},{"id":"76909088-3363-4e12-af51-fe6c35fbeaef","index":421,"period":1,"minute":10,"second":15,"timestamp":"00:10:15.597","team":"Bolivia","player":"Marcelo Sebastián Suárez Justiniano","type":"Pressure","location":[12.2,5.8],"endLocation":null,"outcome":null,"possession":21,"xg":null},{"id":"81fa5cd9-594d-4582-aeff-d47d883980e7","index":440,"period":1,"minute":11,"second":21,"timestamp":"00:11:21.872","team":"Bolivia","player":"Yomar Rene Rocha Rodriguez","type":"Pressure","location":[25.7,67.1],"endLocation":null,"outcome":null,"possession":24,"xg":null},{"id":"8c73c1ae-d8d7-497e-bb28-6475762a329f","index":455,"period":1,"minute":11,"second":31,"timestamp":"00:11:31.249","team":"Bolivia","player":"Gabriel Alejandro Villamíl Cortéz","type":"Pressure","location":[37.1,58.4],"endLocation":null,"outcome":null,"possession":24,"xg":null},{"id":"151657d8-b170-4d33-95df-0a3cc44ef790","index":465,"period":1,"minute":11,"second":38,"timestamp":"00:11:38.906","team":"Bolivia","player":"Miguel Ángel Terceros","type":"Pressure","location":[42.8,74.6],"endLocation":null,"outcome":null,"possession":24,"xg":null},{"id":"aa4abf87-6445-482f-a8ed-34e7d4b51afd","index":484,"period":1,"minute":11,"second":58,"timestamp":"00:11:58.408","team":"Bolivia","player":"Miguel Ángel Terceros","type":"Pressure","location":[35.7,66.2],"endLocation":null,"outcome":null,"possession":24,"xg":null},{"id":"2e6f4373-6c19-4e10-8332-e4330d2b06a2","index":500,"period":1,"minute":12,"second":31,"timestamp":"00:12:31.217","team":"Panama","player":"José Ángel Córdoba Chambers","type":"Pressure","location":[51.8,43.8],"endLocation":null,"outcome":null,"possession":26,"xg":null},{"id":"d64782f8-fa33-46ff-8762-a3c16a1c9789","index":501,"period":1,"minute":12,"second":31,"timestamp":"00:12:31.276","team":"Panama","player":"Cristian Jesús Martínez","type":"Pressure","location":[57.3,47.6],"endLocation":null,"outcome":null,"possession":26,"xg":null},{"id":"74250072-be92-482c-b337-12b8d8c99734","index":503,"period":1,"minute":12,"second":32,"timestamp":"00:12:32.316","team":"Panama","player":"Jovani Francisco Welch Lopez","type":"Pressure","location":[50.8,39],"endLocation":null,"outcome":null,"possession":26,"xg":null},{"id":"f9066c72-50c2-4ded-a3ec-76c7c9c1bfb0","index":514,"period":1,"minute":12,"second":39,"timestamp":"00:12:39.620","team":"Bolivia","player":"Carmelo Algarañaz Añez","type":"Pressure","location":[86.5,33.3],"endLocation":null,"outcome":null,"possession":27,"xg":null},{"id":"e0b02d36-fcf2-4312-aa7c-ef0cc21a8f7a","index":527,"period":1,"minute":12,"second":45,"timestamp":"00:12:45.919","team":"Bolivia","player":"José Manuel Sagredo Chávez","type":"Pressure","location":[54.8,8.2],"endLocation":null,"outcome":null,"possession":27,"xg":null},{"id":"b975ab21-a255-4720-93c4-1fa834f0917f","index":546,"period":1,"minute":13,"second":10,"timestamp":"00:13:10.687","team":"Bolivia","player":"Boris Cespedes","type":"Pressure","location":[54.9,61],"endLocation":null,"outcome":null,"possession":27,"xg":null},{"id":"0466d4dc-8b61-4c9d-9992-4d9b46aaf7b0","index":551,"period":1,"minute":13,"second":13,"timestamp":"00:13:13.891","team":"Panama","player":"Edgar Yoel Bárcenas Herrera","type":"Pressure","location":[88.5,20.1],"endLocation":null,"outcome":null,"possession":27,"xg":null},{"id":"dd90806d-d79a-41fb-8a34-351aab519627","index":560,"period":1,"minute":13,"second":21,"timestamp":"00:13:21.871","team":"Panama","player":"José Fajardo Nelson","type":"Pressure","location":[95.5,31.5],"endLocation":null,"outcome":null,"possession":28,"xg":null},{"id":"1e548393-8885-4240-9a2d-cf7275109359","index":565,"period":1,"minute":13,"second":23,"timestamp":"00:13:23.722","team":"Panama","player":"César Rodolfo Blackman Camarena","type":"Pressure","location":[100.7,50.9],"endLocation":null,"outcome":null,"possession":28,"xg":null},{"id":"4e6f921d-e466-4b01-8cf6-d850d25a35de","index":590,"period":1,"minute":13,"second":44,"timestamp":"00:13:44.240","team":"Panama","player":"José Fajardo Nelson","type":"Pressure","location":[108.8,22.4],"endLocation":null,"outcome":null,"possession":28,"xg":null},{"id":"9a796760-69db-4edb-9bf0-9b29a74cb10c","index":620,"period":1,"minute":15,"second":29,"timestamp":"00:15:29.421","team":"Bolivia","player":"Yomar Rene Rocha Rodriguez","type":"Pressure","location":[94.8,60.9],"endLocation":null,"outcome":null,"possession":30,"xg":null},{"id":"794c251a-81cb-4545-aaa4-9241aebfd078","index":625,"period":1,"minute":15,"second":32,"timestamp":"00:15:32.010","team":"Bolivia","player":"Yomar Rene Rocha Rodriguez","type":"Pressure","location":[107.8,42.5],"endLocation":null,"outcome":null,"possession":30,"xg":null},{"id":"fb430e90-bf03-4643-a08d-c6dabc44c7ba","index":629,"period":1,"minute":15,"second":38,"timestamp":"00:15:38.918","team":"Panama","player":"Cristian Jesús Martínez","type":"Pressure","location":[86.7,73.7],"endLocation":null,"outcome":null,"possession":30,"xg":null},{"id":"d886dcc9-a17e-464c-99b5-b9605c065688","index":635,"period":1,"minute":15,"second":40,"timestamp":"00:15:40.592","team":"Bolivia","player":"José Manuel Sagredo Chávez","type":"Pressure","location":[35.7,14.4],"endLocation":null,"outcome":null,"possession":30,"xg":null},{"id":"ccaa7a05-422a-4990-bb61-e8f3d47e8142","index":646,"period":1,"minute":16,"second":17,"timestamp":"00:16:17.089","team":"Panama","player":"Edgar Yoel Bárcenas Herrera","type":"Pressure","location":[100.2,4.2],"endLocation":null,"outcome":null,"possession":31,"xg":null},{"id":"94a7a772-25e7-4522-8cc8-3565f1baa973","index":650,"period":1,"minute":16,"second":18,"timestamp":"00:16:18.912","team":"Panama","player":"Jovani Francisco Welch Lopez","type":"Pressure","location":[90.5,5.1],"endLocation":null,"outcome":null,"possession":31,"xg":null},{"id":"22b33bb4-9392-455a-9703-f72f51307c9d","index":656,"period":1,"minute":16,"second":20,"timestamp":"00:16:20.519","team":"Panama","player":"José Fajardo Nelson","type":"Pressure","location":[101.9,10.6],"endLocation":null,"outcome":null,"possession":31,"xg":null},{"id":"4c34fe07-702e-460a-b3dd-acca212f3f2d","index":665,"period":1,"minute":16,"second":30,"timestamp":"00:16:30.733","team":"Bolivia","player":"Miguel Ángel Terceros","type":"Pressure","location":[66.1,30.8],"endLocation":null,"outcome":null,"possession":31,"xg":null},{"id":"ca055ad7-d447-42ad-ac9a-b706fd6660e7","index":669,"period":1,"minute":16,"second":34,"timestamp":"00:16:34.027","team":"Panama","player":"Michael Amir Murillo Bermudez","type":"Pressure","location":[70.6,60.9],"endLocation":null,"outcome":null,"possession":31,"xg":null},{"id":"d6fa9666-2b84-41e2-9e66-c3aec5876c0b","index":674,"period":1,"minute":16,"second":38,"timestamp":"00:16:38.082","team":"Panama","player":"Jovani Francisco Welch Lopez","type":"Pressure","location":[52.9,66.4],"endLocation":null,"outcome":null,"possession":31,"xg":null},{"id":"a96a0fc3-6737-4b7f-b0f7-edf5e9f8b544","index":694,"period":1,"minute":17,"second":27,"timestamp":"00:17:27.956","team":"Bolivia","player":"Carmelo Algarañaz Añez","type":"Pressure","location":[99.6,41.8],"endLocation":null,"outcome":null,"possession":32,"xg":null},{"id":"6306927b-fbcf-428c-9b6c-66192e7bafdd","index":702,"period":1,"minute":18,"second":7,"timestamp":"00:18:07.141","team":"Panama","player":"César Rodolfo Blackman Camarena","type":"Pressure","location":[82.3,73.6],"endLocation":null,"outcome":null,"possession":33,"xg":null},{"id":"a9fb49f1-8e7b-45cb-bddb-33e0bc5af91c","index":711,"period":1,"minute":18,"second":30,"timestamp":"00:18:30.044","team":"Panama","player":"Cristian Jesús Martínez","type":"Pressure","location":[39.2,68.8],"endLocation":null,"outcome":null,"possession":34,"xg":null},{"id":"1187e546-d0e8-4095-a293-5a6fe9c93bba","index":712,"period":1,"minute":18,"second":30,"timestamp":"00:18:30.200","team":"Panama","player":"César Rodolfo Blackman Camarena","type":"Pressure","location":[44.3,71.9],"endLocation":null,"outcome":null,"possession":34,"xg":null},{"id":"ca8e7451-0eed-4a43-b390-2677891ef5da","index":723,"period":1,"minute":18,"second":41,"timestamp":"00:18:41.814","team":"Panama","player":"José Ángel Córdoba Chambers","type":"Pressure","location":[36.6,33.6],"endLocation":null,"outcome":null,"possession":34,"xg":null},{"id":"b59116f4-9f7d-4392-b766-1c6856fa327f","index":726,"period":1,"minute":18,"second":43,"timestamp":"00:18:43.058","team":"Panama","player":"Erick Javier Davis Grajales","type":"Pressure","location":[36,16.1],"endLocation":null,"outcome":null,"possession":34,"xg":null},{"id":"6e3c9f59-8708-4b55-bc26-cd69b11bec91","index":751,"period":1,"minute":21,"second":4,"timestamp":"00:21:04.685","team":"Bolivia","player":"Carmelo Algarañaz Añez","type":"Pressure","location":[102.2,37.5],"endLocation":null,"outcome":null,"possession":37,"xg":null},{"id":"02ebd322-037d-42df-a9f4-fa26e001f689","index":753,"period":1,"minute":21,"second":8,"timestamp":"00:21:08.691","team":"Bolivia","player":"Héctor Manuel Cuellar Rosales","type":"Pressure","location":[37.8,49.4],"endLocation":null,"outcome":null,"possession":37,"xg":null},{"id":"002e4156-e210-4012-8929-ad7f28b37300","index":764,"period":1,"minute":21,"second":15,"timestamp":"00:21:15.594","team":"Bolivia","player":"Boris Cespedes","type":"Pressure","location":[29.8,67.1],"endLocation":null,"outcome":null,"possession":37,"xg":null},{"id":"183e647b-5e7a-4d7c-9741-d231906da515","index":771,"period":1,"minute":21,"second":19,"timestamp":"00:21:19.774","team":"Bolivia","player":"Miguel Ángel Terceros","type":"Pressure","location":[45.7,54.8],"endLocation":null,"outcome":null,"possession":37,"xg":null},{"id":"27acc681-f488-4d8a-bcab-5aceb9532e63","index":785,"period":1,"minute":21,"second":34,"timestamp":"00:21:34.010","team":"Bolivia","player":"Héctor Manuel Cuellar Rosales","type":"Pressure","location":[14.9,47],"endLocation":null,"outcome":null,"possession":37,"xg":null},{"id":"6ef9c3f6-30a9-4ac2-a184-2fd2d6e5e880","index":786,"period":1,"minute":21,"second":34,"timestamp":"00:21:34.311","team":"Bolivia","player":"Luis Fernando Haquín Lopez","type":"Pressure","location":[10.7,45.3],"endLocation":null,"outcome":null,"possession":37,"xg":null},{"id":"35b8ad90-be7d-4cf6-8ab5-240b4b07562b","index":800,"period":1,"minute":22,"second":46,"timestamp":"00:22:46.624","team":"Panama","player":"Cristian Jesús Martínez","type":"Pressure","location":[50.3,56],"endLocation":null,"outcome":null,"possession":38,"xg":null},{"id":"0667dce8-f967-44e9-baf4-bbe191819b8f","index":808,"period":1,"minute":22,"second":51,"timestamp":"00:22:51.569","team":"Bolivia","player":"Gabriel Alejandro Villamíl Cortéz","type":"Pressure","location":[62.7,27.3],"endLocation":null,"outcome":null,"possession":39,"xg":null},{"id":"66d6dcae-3f73-44d0-8c55-e234b70b92b0","index":813,"period":1,"minute":22,"second":54,"timestamp":"00:22:54.315","team":"Bolivia","player":"Boris Cespedes","type":"Pressure","location":[40.9,40.8],"endLocation":null,"outcome":null,"possession":39,"xg":null},{"id":"f805bd72-b1fe-480f-9356-5f183992f1b0","index":816,"period":1,"minute":22,"second":55,"timestamp":"00:22:55.828","team":"Bolivia","player":"Gabriel Alejandro Villamíl Cortéz","type":"Pressure","location":[24,29.9],"endLocation":null,"outcome":null,"possession":39,"xg":null},{"id":"fb584e2f-f7ea-4c60-ba2e-9d275eafac92","index":830,"period":1,"minute":23,"second":10,"timestamp":"00:23:10.682","team":"Panama","player":"José Fajardo Nelson","type":"Pressure","location":[82.5,19.8],"endLocation":null,"outcome":null,"possession":40,"xg":null},{"id":"218cfdfe-a465-409f-95df-af44cc186a4e","index":843,"period":1,"minute":23,"second":39,"timestamp":"00:23:39.314","team":"Bolivia","player":"Carmelo Algarañaz Añez","type":"Pressure","location":[104.3,35.9],"endLocation":null,"outcome":null,"possession":41,"xg":null},{"id":"8b6fd195-9d80-4c43-be61-84ca9042c0d7","index":845,"period":1,"minute":23,"second":43,"timestamp":"00:23:43.878","team":"Bolivia","player":"Luis Fernando Haquín Lopez","type":"Pressure","location":[33.6,43.9],"endLocation":null,"outcome":null,"possession":41,"xg":null},{"id":"fc832c10-47c5-4bb2-9d00-2f46761f4fca","index":877,"period":1,"minute":24,"second":25,"timestamp":"00:24:25.081","team":"Panama","player":"César Rodolfo Blackman Camarena","type":"Pressure","location":[81.8,62.4],"endLocation":null,"outcome":null,"possession":42,"xg":null},{"id":"d5824875-6637-4866-a23e-daea1c6440fc","index":884,"period":1,"minute":24,"second":32,"timestamp":"00:24:32.248","team":"Panama","player":"Jovani Francisco Welch Lopez","type":"Pressure","location":[43,30.7],"endLocation":null,"outcome":null,"possession":42,"xg":null},{"id":"36cd7a7d-e03e-4bf1-b449-923d6c7f4613","index":907,"period":1,"minute":25,"second":36,"timestamp":"00:25:36.938","team":"Bolivia","player":"Luis Fernando Haquín Lopez","type":"Pressure","location":[32.9,25],"endLocation":null,"outcome":null,"possession":45,"xg":null},{"id":"21f45169-ef23-42f4-be17-f66266356527","index":912,"period":1,"minute":25,"second":38,"timestamp":"00:25:38.841","team":"Bolivia","player":"Luis Fernando Haquín Lopez","type":"Pressure","location":[38.1,31.1],"endLocation":null,"outcome":null,"possession":45,"xg":null},{"id":"0ff84df1-5901-4152-a0cb-7019cd768253","index":925,"period":1,"minute":25,"second":51,"timestamp":"00:25:51.058","team":"Bolivia","player":"Miguel Ángel Terceros","type":"Pressure","location":[30,71.6],"endLocation":null,"outcome":null,"possession":45,"xg":null},{"id":"1829eb69-59b1-4470-9d74-f3ae4d41d015","index":937,"period":1,"minute":26,"second":4,"timestamp":"00:26:04.398","team":"Panama","player":"Carlos Miguel Harvey Cesneros","type":"Pressure","location":[45.6,34.3],"endLocation":null,"outcome":null,"possession":45,"xg":null},{"id":"ec42b731-6edc-479f-abd1-0562425a61f1","index":945,"period":1,"minute":28,"second":3,"timestamp":"00:28:03.101","team":"Bolivia","player":"Héctor Manuel Cuellar Rosales","type":"Pressure","location":[49.2,68.3],"endLocation":null,"outcome":null,"possession":47,"xg":null},{"id":"7046fc1e-ebe9-4fe5-ac4b-4f39b830db0a","index":951,"period":1,"minute":28,"second":7,"timestamp":"00:28:07.790","team":"Panama","player":"Edgar Yoel Bárcenas Herrera","type":"Pressure","location":[95.6,31.4],"endLocation":null,"outcome":null,"possession":47,"xg":null},{"id":"40a6bd55-755c-4e2c-8106-fa44f2cf0ce4","index":964,"period":1,"minute":29,"second":22,"timestamp":"00:29:22.087","team":"Bolivia","player":"Carmelo Algarañaz Añez","type":"Pressure","location":[29.8,57.4],"endLocation":null,"outcome":null,"possession":48,"xg":null},{"id":"e54158e2-febf-4ab4-b3ca-c0e8fa8ceb62","index":1007,"period":1,"minute":31,"second":44,"timestamp":"00:31:44.190","team":"Panama","player":"Edgar Yoel Bárcenas Herrera","type":"Pressure","location":[72.8,4.7],"endLocation":null,"outcome":null,"possession":51,"xg":null},{"id":"fc025faa-2b0f-47c9-b921-8f2faf232fe3","index":1030,"period":1,"minute":32,"second":12,"timestamp":"00:32:12.182","team":"Bolivia","player":"Marcelo Sebastián Suárez Justiniano","type":"Pressure","location":[29.7,7.5],"endLocation":null,"outcome":null,"possession":52,"xg":null},{"id":"62f4d029-fd1f-4135-9121-b2368947dcbd","index":1032,"period":1,"minute":32,"second":13,"timestamp":"00:32:13.896","team":"Bolivia","player":"Ramiro Vaca Ponce","type":"Pressure","location":[52.9,8.5],"endLocation":null,"outcome":null,"possession":52,"xg":null},{"id":"f3a462ba-9ada-41e5-8691-d9d4258ee9fd","index":1036,"period":1,"minute":32,"second":17,"timestamp":"00:32:17.093","team":"Bolivia","player":"Luis Fernando Haquín Lopez","type":"Pressure","location":[13,18.2],"endLocation":null,"outcome":null,"possession":52,"xg":null},{"id":"7613dd13-0f61-4234-b171-11cd9a703b2b","index":1042,"period":1,"minute":32,"second":19,"timestamp":"00:32:19.206","team":"Bolivia","player":"Marcelo Sebastián Suárez Justiniano","type":"Pressure","location":[5.9,26],"endLocation":null,"outcome":null,"possession":52,"xg":null},{"id":"970f5705-236a-4d0d-b3d5-344cbd529121","index":1072,"period":1,"minute":33,"second":15,"timestamp":"00:33:15.580","team":"Panama","player":"Erick Javier Davis Grajales","type":"Pressure","location":[41.9,38.5],"endLocation":null,"outcome":null,"possession":54,"xg":null},{"id":"7af0e58b-a631-4622-8fc7-eb1a50b9a032","index":1091,"period":1,"minute":33,"second":57,"timestamp":"00:33:57.478","team":"Bolivia","player":"José Manuel Sagredo Chávez","type":"Pressure","location":[100,7.5],"endLocation":null,"outcome":null,"possession":55,"xg":null},{"id":"6b6f26ea-0e14-4fc9-8dc0-6f6f265ed491","index":1095,"period":1,"minute":34,"second":2,"timestamp":"00:34:02.412","team":"Panama","player":"Michael Amir Murillo Bermudez","type":"Pressure","location":[8,68.4],"endLocation":null,"outcome":null,"possession":55,"xg":null},{"id":"8a58d284-8f31-466c-848c-af05cac3bdda","index":1100,"period":1,"minute":34,"second":7,"timestamp":"00:34:07.895","team":"Bolivia","player":"Ramiro Vaca Ponce","type":"Pressure","location":[109.3,7.8],"endLocation":null,"outcome":null,"possession":55,"xg":null},{"id":"8ddc52ab-a2a7-4c1d-a6a4-17cb7364b1ed","index":1105,"period":1,"minute":34,"second":11,"timestamp":"00:34:11.829","team":"Bolivia","player":"Marcelo Sebastián Suárez Justiniano","type":"Pressure","location":[72.3,9.1],"endLocation":null,"outcome":null,"possession":55,"xg":null},{"id":"ae0725cb-3ab6-4c04-825b-32ed43fc668d","index":1113,"period":1,"minute":34,"second":15,"timestamp":"00:34:15.611","team":"Panama","player":"José Fajardo Nelson","type":"Pressure","location":[77.1,59.1],"endLocation":null,"outcome":null,"possession":55,"xg":null},{"id":"c5280530-30ee-496d-a8f7-8d2c70d182c4","index":1114,"period":1,"minute":34,"second":15,"timestamp":"00:34:15.843","team":"Panama","player":"Cristian Jesús Martínez","type":"Pressure","location":[75,60.5],"endLocation":null,"outcome":null,"possession":55,"xg":null},{"id":"1df21d7a-8d01-4eed-bddf-4519c382ecf2","index":1139,"period":1,"minute":34,"second":41,"timestamp":"00:34:41.367","team":"Bolivia","player":"José Manuel Sagredo Chávez","type":"Pressure","location":[27.7,8],"endLocation":null,"outcome":null,"possession":55,"xg":null},{"id":"859bc45c-210f-40ae-9242-ab17fd254a71","index":1154,"period":1,"minute":34,"second":49,"timestamp":"00:34:49.448","team":"Bolivia","player":"Gabriel Alejandro Villamíl Cortéz","type":"Pressure","location":[53.2,35.6],"endLocation":null,"outcome":null,"possession":55,"xg":null},{"id":"fa8eb357-98b8-40ec-8e2d-f7fc10c8e6df","index":1166,"period":1,"minute":35,"second":5,"timestamp":"00:35:05.738","team":"Bolivia","player":"Marcelo Sebastián Suárez Justiniano","type":"Pressure","location":[25.5,21],"endLocation":null,"outcome":null,"possession":55,"xg":null},{"id":"1b440dd3-16b7-4988-bcc5-2c86937acefe","index":1175,"period":1,"minute":35,"second":13,"timestamp":"00:35:13.484","team":"Bolivia","player":"Héctor Manuel Cuellar Rosales","type":"Pressure","location":[11.8,48],"endLocation":null,"outcome":null,"possession":55,"xg":null},{"id":"a71869de-9a30-4189-8414-3d3085ce645e","index":1200,"period":1,"minute":35,"second":32,"timestamp":"00:35:32.092","team":"Panama","player":"Jovani Francisco Welch Lopez","type":"Pressure","location":[87,43.5],"endLocation":null,"outcome":null,"possession":56,"xg":null},{"id":"65b17a51-762e-4f60-99c4-957078f7a6be","index":1210,"period":1,"minute":35,"second":40,"timestamp":"00:35:40.631","team":"Panama","player":"Edgardo Isaac Fariña Wynter","type":"Pressure","location":[90.4,58.6],"endLocation":null,"outcome":null,"possession":56,"xg":null},{"id":"1a06fcf5-d3d7-48c1-8bf7-aba5e5ddeb2b","index":1230,"period":1,"minute":35,"second":54,"timestamp":"00:35:54.071","team":"Panama","player":"Jovani Francisco Welch Lopez","type":"Pressure","location":[73,42.5],"endLocation":null,"outcome":null,"possession":56,"xg":null},{"id":"b76e7625-1599-4c0b-b0b3-2d5cc4d19414","index":1252,"period":1,"minute":36,"second":27,"timestamp":"00:36:27.824","team":"Bolivia","player":"Ramiro Vaca Ponce","type":"Pressure","location":[101.4,16.7],"endLocation":null,"outcome":null,"possession":57,"xg":null},{"id":"e3db00b9-bfe7-4a71-a7e8-300d90e9e275","index":1261,"period":1,"minute":36,"second":35,"timestamp":"00:36:35.338","team":"Bolivia","player":"Marcelo Sebastián Suárez Justiniano","type":"Pressure","location":[63.4,13.9],"endLocation":null,"outcome":null,"possession":57,"xg":null},{"id":"ecc9c395-cea4-4672-b90f-7886c4e415ec","index":1264,"period":1,"minute":36,"second":36,"timestamp":"00:36:36.203","team":"Bolivia","player":"Ramiro Vaca Ponce","type":"Pressure","location":[72.6,15.8],"endLocation":null,"outcome":null,"possession":57,"xg":null},{"id":"fbe4d549-9634-4f24-8db4-7764d4a2c3a8","index":1271,"period":1,"minute":36,"second":39,"timestamp":"00:36:39.471","team":"Bolivia","player":"Ramiro Vaca Ponce","type":"Pressure","location":[85.8,20],"endLocation":null,"outcome":null,"possession":57,"xg":null},{"id":"e483d5f2-eec9-4c32-994b-2681bd470752","index":1273,"period":1,"minute":36,"second":40,"timestamp":"00:36:40.749","team":"Bolivia","player":"Gabriel Alejandro Villamíl Cortéz","type":"Pressure","location":[71.6,23.4],"endLocation":null,"outcome":null,"possession":57,"xg":null},{"id":"5a87fb2a-b254-4020-ba9b-484a3a0a81ac","index":1278,"period":1,"minute":36,"second":43,"timestamp":"00:36:43.270","team":"Bolivia","player":"Marcelo Sebastián Suárez Justiniano","type":"Pressure","location":[74,16.5],"endLocation":null,"outcome":null,"possession":57,"xg":null},{"id":"113e0f9a-121c-47da-828d-ba74dabcfc3a","index":1307,"period":1,"minute":37,"second":21,"timestamp":"00:37:21.185","team":"Bolivia","player":"Yomar Rene Rocha Rodriguez","type":"Pressure","location":[116.3,74.6],"endLocation":null,"outcome":null,"possession":58,"xg":null},{"id":"a77ce9bf-3260-4b5d-ae48-4c4387065e14","index":1320,"period":1,"minute":37,"second":39,"timestamp":"00:37:39.184","team":"Panama","player":"José Ángel Córdoba Chambers","type":"Pressure","location":[6.9,27.6],"endLocation":null,"outcome":null,"possession":59,"xg":null},{"id":"848520fa-1868-4063-b3d7-97c239b5f02a","index":1336,"period":1,"minute":38,"second":55,"timestamp":"00:38:55.433","team":"Bolivia","player":"Carmelo Algarañaz Añez","type":"Pressure","location":[111.8,45.6],"endLocation":null,"outcome":null,"possession":61,"xg":null},{"id":"3a67b496-8fcc-41f9-9b74-c15935f15c2a","index":1343,"period":1,"minute":39,"second":2,"timestamp":"00:39:02.893","team":"Bolivia","player":"Gabriel Alejandro Villamíl Cortéz","type":"Pressure","location":[34.5,14.1],"endLocation":null,"outcome":null,"possession":61,"xg":null},{"id":"787eca51-92a9-4cab-b236-a1533dce84c6","index":1350,"period":1,"minute":39,"second":7,"timestamp":"00:39:07.574","team":"Panama","player":"César Rodolfo Blackman Camarena","type":"Pressure","location":[92.2,54.9],"endLocation":null,"outcome":null,"possession":61,"xg":null},{"id":"d1f1ece1-4a4c-4201-bb1a-884aa0f76bde","index":1363,"period":1,"minute":39,"second":18,"timestamp":"00:39:18.079","team":"Panama","player":"Edgar Yoel Bárcenas Herrera","type":"Pressure","location":[70.9,52],"endLocation":null,"outcome":null,"possession":62,"xg":null},{"id":"f61f21a4-5293-4287-8ce5-30e5cea2d2ba","index":1402,"period":1,"minute":40,"second":7,"timestamp":"00:40:07.235","team":"Panama","player":"César Rodolfo Blackman Camarena","type":"Pressure","location":[63.2,63.8],"endLocation":null,"outcome":null,"possession":62,"xg":null},{"id":"97338be2-01b8-4cb4-aacc-1c866f645a4d","index":1412,"period":1,"minute":40,"second":20,"timestamp":"00:40:20.583","team":"Bolivia","player":"Carmelo Algarañaz Añez","type":"Pressure","location":[82,39.4],"endLocation":null,"outcome":null,"possession":63,"xg":null},{"id":"32b7c712-29c6-4eb1-b6d4-0bbe23fb35a4","index":1443,"period":1,"minute":40,"second":57,"timestamp":"00:40:57.851","team":"Bolivia","player":"Marcelo Sebastián Suárez Justiniano","type":"Pressure","location":[31.7,8.4],"endLocation":null,"outcome":null,"possession":63,"xg":null},{"id":"a4411ea1-8e72-4d83-a766-0cdd2c4bb20c","index":1445,"period":1,"minute":40,"second":59,"timestamp":"00:40:59.514","team":"Bolivia","player":"José Manuel Sagredo Chávez","type":"Pressure","location":[31,17.5],"endLocation":null,"outcome":null,"possession":63,"xg":null},{"id":"dab41264-45f4-4b27-a721-607556e22d1b","index":1448,"period":1,"minute":41,"second":1,"timestamp":"00:41:01.759","team":"Bolivia","player":"José Manuel Sagredo Chávez","type":"Pressure","location":[11.1,12.2],"endLocation":null,"outcome":null,"possession":63,"xg":null},{"id":"cd8d6471-5280-492d-977a-c69cb6384faa","index":1471,"period":1,"minute":43,"second":4,"timestamp":"00:43:04.015","team":"Bolivia","player":"Gabriel Alejandro Villamíl Cortéz","type":"Pressure","location":[29.7,46.7],"endLocation":null,"outcome":null,"possession":65,"xg":null},{"id":"6c1871e0-9c0e-484f-ab6c-8df314d9a7b6","index":1472,"period":1,"minute":43,"second":4,"timestamp":"00:43:04.330","team":"Bolivia","player":"Ramiro Vaca Ponce","type":"Pressure","location":[30,46.5],"endLocation":null,"outcome":null,"possession":65,"xg":null},{"id":"d53ff8b7-4b5a-49cb-96a0-3fdb074b3dac","index":1483,"period":1,"minute":43,"second":10,"timestamp":"00:43:10.983","team":"Panama","player":"Jovani Francisco Welch Lopez","type":"Pressure","location":[60.1,4.5],"endLocation":null,"outcome":null,"possession":66,"xg":null},{"id":"023b787a-436f-4362-b464-737ca055340e","index":1495,"period":1,"minute":43,"second":29,"timestamp":"00:43:29.747","team":"Panama","player":"Edgardo Isaac Fariña Wynter","type":"Pressure","location":[64.1,26.5],"endLocation":null,"outcome":null,"possession":67,"xg":null},{"id":"89258fab-cf2e-4818-9d22-9487f67f540e","index":1516,"period":1,"minute":44,"second":1,"timestamp":"00:44:01.111","team":"Panama","player":"Jovani Francisco Welch Lopez","type":"Pressure","location":[53,10.6],"endLocation":null,"outcome":null,"possession":68,"xg":null},{"id":"b425ea44-21c9-4aca-8001-04d65e5901a3","index":1526,"period":1,"minute":44,"second":7,"timestamp":"00:44:07.234","team":"Panama","player":"Cristian Jesús Martínez","type":"Pressure","location":[38.5,43.7],"endLocation":null,"outcome":null,"possession":68,"xg":null},{"id":"5a869157-8df6-4baf-9975-2c6b5f299ff2","index":1531,"period":1,"minute":44,"second":10,"timestamp":"00:44:10.094","team":"Bolivia","player":"Gabriel Alejandro Villamíl Cortéz","type":"Pressure","location":[73,32.3],"endLocation":null,"outcome":null,"possession":69,"xg":null},{"id":"015083b0-5e70-4e41-8f07-36e63cb85a60","index":1554,"period":1,"minute":44,"second":52,"timestamp":"00:44:52.230","team":"Panama","player":"César Rodolfo Blackman Camarena","type":"Pressure","location":[88.2,58],"endLocation":null,"outcome":null,"possession":70,"xg":null},{"id":"f8e2a241-f59f-4d39-9028-4f21a59abf22","index":1558,"period":1,"minute":44,"second":54,"timestamp":"00:44:54.993","team":"Panama","player":"José Fajardo Nelson","type":"Pressure","location":[94.6,56],"endLocation":null,"outcome":null,"possession":70,"xg":null},{"id":"00307baa-bc30-4e5b-9cb8-7e890718e9b5","index":1562,"period":1,"minute":44,"second":57,"timestamp":"00:44:57.960","team":"Panama","player":"Michael Amir Murillo Bermudez","type":"Pressure","location":[81.4,72.9],"endLocation":null,"outcome":null,"possession":70,"xg":null},{"id":"62cdf2da-a96e-408c-8322-9a04672421bd","index":1576,"period":1,"minute":45,"second":17,"timestamp":"00:45:17.972","team":"Panama","player":"Edgardo Isaac Fariña Wynter","type":"Pressure","location":[47.5,44.5],"endLocation":null,"outcome":null,"possession":70,"xg":null},{"id":"dd2e641a-13bf-4c17-b32b-77c58aaf5c00","index":1587,"period":1,"minute":45,"second":27,"timestamp":"00:45:27.828","team":"Bolivia","player":"Ramiro Vaca Ponce","type":"Pressure","location":[78.3,13.6],"endLocation":null,"outcome":null,"possession":71,"xg":null},{"id":"020f3763-95b8-4a5b-ba70-22edeb1336d8","index":1590,"period":1,"minute":45,"second":31,"timestamp":"00:45:31.522","team":"Bolivia","player":"Ramiro Vaca Ponce","type":"Pressure","location":[62.5,7.3],"endLocation":null,"outcome":null,"possession":71,"xg":null},{"id":"5d191863-586a-417b-a89e-64a8f2d26166","index":1638,"period":2,"minute":45,"second":36,"timestamp":"00:00:36.347","team":"Panama","player":"Erick Javier Davis Grajales","type":"Pressure","location":[104,22],"endLocation":null,"outcome":null,"possession":74,"xg":null},{"id":"4aa5d5c1-af73-44dd-b857-550312e2894a","index":1639,"period":2,"minute":45,"second":38,"timestamp":"00:00:38.408","team":"Panama","player":"Erick Javier Davis Grajales","type":"Pressure","location":[110.8,11.9],"endLocation":null,"outcome":null,"possession":74,"xg":null},{"id":"5a58f5ef-b460-4da9-a3ca-d039563cb0bd","index":1644,"period":2,"minute":45,"second":47,"timestamp":"00:00:47.824","team":"Bolivia","player":"Miguel Ángel Terceros","type":"Pressure","location":[21.3,63.4],"endLocation":null,"outcome":null,"possession":75,"xg":null},{"id":"367bf9b7-4deb-4f2e-b78e-1f96bacacea4","index":1658,"period":2,"minute":46,"second":9,"timestamp":"00:01:09.706","team":"Bolivia","player":"Yomar Rene Rocha Rodriguez","type":"Pressure","location":[29.3,56.2],"endLocation":null,"outcome":null,"possession":77,"xg":null},{"id":"44884af4-947f-473c-a302-4e828c3a7c8a","index":1668,"period":2,"minute":46,"second":18,"timestamp":"00:01:18.810","team":"Bolivia","player":"Marcelo Sebastián Suárez Justiniano","type":"Pressure","location":[19.7,8.3],"endLocation":null,"outcome":null,"possession":77,"xg":null},{"id":"bcd57f0c-3337-486b-8069-9001119e8711","index":1672,"period":2,"minute":46,"second":21,"timestamp":"00:01:21.510","team":"Bolivia","player":"José Manuel Sagredo Chávez","type":"Pressure","location":[9,16.5],"endLocation":null,"outcome":null,"possession":77,"xg":null},{"id":"95baed66-aefc-4e7d-a7c6-1bb08d543dc3","index":1676,"period":2,"minute":46,"second":22,"timestamp":"00:01:22.902","team":"Bolivia","player":"Marcelo Sebastián Suárez Justiniano","type":"Pressure","location":[9.3,21.5],"endLocation":null,"outcome":null,"possession":77,"xg":null},{"id":"3213307f-5cca-4239-bda3-8ae4d21cf4f6","index":1692,"period":2,"minute":46,"second":54,"timestamp":"00:01:54.828","team":"Bolivia","player":"Carmelo Algarañaz Añez","type":"Pressure","location":[55.9,59.4],"endLocation":null,"outcome":null,"possession":78,"xg":null},{"id":"d276a70e-a814-4faf-a12e-9d5490fb262a","index":1695,"period":2,"minute":46,"second":56,"timestamp":"00:01:56.963","team":"Bolivia","player":"Ramiro Vaca Ponce","type":"Pressure","location":[54.2,36.7],"endLocation":null,"outcome":null,"possession":78,"xg":null},{"id":"8da55d73-3004-47ea-9ff9-6788df3d0660","index":1699,"period":2,"minute":46,"second":59,"timestamp":"00:01:59.652","team":"Bolivia","player":"José Manuel Sagredo Chávez","type":"Pressure","location":[67.1,28.5],"endLocation":null,"outcome":null,"possession":79,"xg":null},{"id":"8166c4c1-a8ac-4370-ba48-12e003a2e30e","index":1741,"period":2,"minute":47,"second":56,"timestamp":"00:02:56.520","team":"Panama","player":"José Fajardo Nelson","type":"Pressure","location":[109.7,34.6],"endLocation":null,"outcome":null,"possession":80,"xg":null},{"id":"b62e11e3-288b-4fc8-bbab-b7c6cfa48db2","index":1758,"period":2,"minute":48,"second":16,"timestamp":"00:03:16.323","team":"Bolivia","player":"Ramiro Vaca Ponce","type":"Pressure","location":[68.7,43.4],"endLocation":null,"outcome":null,"possession":81,"xg":null},{"id":"80b7c97b-abb6-4570-9717-92f9d4dc27c8","index":1769,"period":2,"minute":48,"second":26,"timestamp":"00:03:26.887","team":"Bolivia","player":"Marcelo Sebastián Suárez Justiniano","type":"Pressure","location":[57.3,8.3],"endLocation":null,"outcome":null,"possession":81,"xg":null},{"id":"9a435ded-b86b-442c-b33f-443cebb054ba","index":1779,"period":2,"minute":48,"second":59,"timestamp":"00:03:59.127","team":"Bolivia","player":"Luis Fernando Haquín Lopez","type":"Pressure","location":[40.8,55.9],"endLocation":null,"outcome":null,"possession":82,"xg":null},{"id":"32c76bd4-5129-468a-8f8a-53f0a3833c97","index":1799,"period":2,"minute":49,"second":16,"timestamp":"00:04:16.134","team":"Bolivia","player":"Gabriel Alejandro Villamíl Cortéz","type":"Pressure","location":[8.1,5.8],"endLocation":null,"outcome":null,"possession":82,"xg":null},{"id":"3597135a-f20c-49e2-a297-f7c13d972f10","index":1812,"period":2,"minute":50,"second":46,"timestamp":"00:05:46.966","team":"Bolivia","player":"Yomar Rene Rocha Rodriguez","type":"Pressure","location":[14.5,74],"endLocation":null,"outcome":null,"possession":83,"xg":null},{"id":"f3c35baf-5371-4b7d-90e3-7f43854e256b","index":1827,"period":2,"minute":51,"second":27,"timestamp":"00:06:27.726","team":"Bolivia","player":"José Manuel Sagredo Chávez","type":"Pressure","location":[32.8,8.9],"endLocation":null,"outcome":null,"possession":84,"xg":null},{"id":"bf640e17-6930-4b3b-b4d9-7f8a3fb20d4f","index":1840,"period":2,"minute":51,"second":43,"timestamp":"00:06:43.209","team":"Bolivia","player":"Miguel Ángel Terceros","type":"Pressure","location":[41.9,21.1],"endLocation":null,"outcome":null,"possession":85,"xg":null},{"id":"997f4d64-c1f0-4ad1-9300-152bcc9ab350","index":1852,"period":2,"minute":52,"second":35,"timestamp":"00:07:35.878","team":"Panama","player":"José Ángel Córdoba Chambers","type":"Pressure","location":[87.5,53.6],"endLocation":null,"outcome":null,"possession":87,"xg":null},{"id":"91097159-d5fb-4aa4-b0f7-6ba17971894d","index":1856,"period":2,"minute":52,"second":37,"timestamp":"00:07:37.924","team":"Panama","player":"José Ángel Córdoba Chambers","type":"Pressure","location":[73.8,62.2],"endLocation":null,"outcome":null,"possession":87,"xg":null},{"id":"be582333-bee9-4bd1-a6da-6f1f6da21d06","index":1861,"period":2,"minute":52,"second":39,"timestamp":"00:07:39.928","team":"Panama","player":"Jovani Francisco Welch Lopez","type":"Pressure","location":[62.8,46.6],"endLocation":null,"outcome":null,"possession":87,"xg":null},{"id":"dbbc2459-ac34-4d82-ab89-abba693fc326","index":1862,"period":2,"minute":52,"second":41,"timestamp":"00:07:41.724","team":"Panama","player":"Carlos Miguel Harvey Cesneros","type":"Pressure","location":[44.6,25.8],"endLocation":null,"outcome":null,"possession":87,"xg":null},{"id":"918b1a88-5d32-409b-8424-284ff87cfd5c","index":1867,"period":2,"minute":52,"second":43,"timestamp":"00:07:43.129","team":"Bolivia","player":"Miguel Ángel Terceros","type":"Pressure","location":[74.1,41.2],"endLocation":null,"outcome":null,"possession":87,"xg":null},{"id":"6186efac-8c6d-4400-a2ee-efb5aa8def1a","index":1878,"period":2,"minute":52,"second":53,"timestamp":"00:07:53.452","team":"Panama","player":"Cristian Jesús Martínez","type":"Pressure","location":[67.6,40.4],"endLocation":null,"outcome":null,"possession":87,"xg":null},{"id":"a6f9e40d-f167-477e-b347-4990d162b682","index":1882,"period":2,"minute":52,"second":56,"timestamp":"00:07:56.368","team":"Panama","player":"Cristian Jesús Martínez","type":"Pressure","location":[80.7,24.2],"endLocation":null,"outcome":null,"possession":87,"xg":null},{"id":"99ae3c05-f184-46dd-adc7-a1821857a2bd","index":1909,"period":2,"minute":53,"second":23,"timestamp":"00:08:23.470","team":"Panama","player":"Jovani Francisco Welch Lopez","type":"Pressure","location":[47,45.8],"endLocation":null,"outcome":null,"possession":87,"xg":null},{"id":"74180724-f917-4aa4-9ad0-06903250537b","index":1910,"period":2,"minute":53,"second":24,"timestamp":"00:08:24.890","team":"Panama","player":"José Ángel Córdoba Chambers","type":"Pressure","location":[40.1,49],"endLocation":null,"outcome":null,"possession":87,"xg":null},{"id":"115da56b-e187-4d74-903e-fce80360783d","index":1935,"period":2,"minute":54,"second":40,"timestamp":"00:09:40.628","team":"Bolivia","player":"José Manuel Sagredo Chávez","type":"Pressure","location":[37.4,11.3],"endLocation":null,"outcome":null,"possession":89,"xg":null},{"id":"bb652f48-765b-44a3-aa6d-f1a1d942cbde","index":1955,"period":2,"minute":56,"second":9,"timestamp":"00:11:09.571","team":"Bolivia","player":"Boris Cespedes","type":"Pressure","location":[69.3,59],"endLocation":null,"outcome":null,"possession":91,"xg":null},{"id":"b000e122-16d1-4e69-a466-d343482bfda4","index":1971,"period":2,"minute":56,"second":30,"timestamp":"00:11:30.220","team":"Bolivia","player":"José Manuel Sagredo Chávez","type":"Pressure","location":[62.7,2.3],"endLocation":null,"outcome":null,"possession":91,"xg":null},{"id":"c64acc2f-e088-4200-8f25-72cf5e42d023","index":1978,"period":2,"minute":56,"second":36,"timestamp":"00:11:36.695","team":"Bolivia","player":"Marcelo Sebastián Suárez Justiniano","type":"Pressure","location":[56.1,19.8],"endLocation":null,"outcome":null,"possession":91,"xg":null},{"id":"47414842-5bbf-4d52-87bc-9ac134a66185","index":1980,"period":2,"minute":56,"second":38,"timestamp":"00:11:38.184","team":"Bolivia","player":"Carmelo Algarañaz Añez","type":"Pressure","location":[67.3,29.7],"endLocation":null,"outcome":null,"possession":91,"xg":null},{"id":"90d84e42-e3bc-46d1-a63a-7c453452156e","index":1998,"period":2,"minute":57,"second":2,"timestamp":"00:12:02.740","team":"Panama","player":"Erick Javier Davis Grajales","type":"Pressure","location":[55.8,4.4],"endLocation":null,"outcome":null,"possession":92,"xg":null},{"id":"e40a1d48-4eee-4891-b538-c817d805ec79","index":2003,"period":2,"minute":57,"second":4,"timestamp":"00:12:04.691","team":"Bolivia","player":"Miguel Ángel Terceros","type":"Pressure","location":[62.3,74],"endLocation":null,"outcome":null,"possession":92,"xg":null},{"id":"b2490af3-5450-445d-aa53-2288ef74af26","index":2007,"period":2,"minute":57,"second":6,"timestamp":"00:12:06.079","team":"Panama","player":"Edgar Yoel Bárcenas Herrera","type":"Pressure","location":[62.1,15.9],"endLocation":null,"outcome":null,"possession":92,"xg":null},{"id":"118ca146-1c56-41df-8313-f6ede8cc22cf","index":2008,"period":2,"minute":57,"second":7,"timestamp":"00:12:07.047","team":"Panama","player":"Cristian Jesús Martínez","type":"Pressure","location":[64,20.1],"endLocation":null,"outcome":null,"possession":92,"xg":null},{"id":"07d92ec8-7e42-42f8-8c47-81e48b1f23ae","index":2015,"period":2,"minute":57,"second":9,"timestamp":"00:12:09.742","team":"Panama","player":"Jovani Francisco Welch Lopez","type":"Pressure","location":[62.4,23.1],"endLocation":null,"outcome":null,"possession":92,"xg":null},{"id":"16c639a5-1264-4d85-b552-1985921a8e15","index":2019,"period":2,"minute":57,"second":13,"timestamp":"00:12:13.333","team":"Bolivia","player":"Yomar Rene Rocha Rodriguez","type":"Pressure","location":[86.2,57.3],"endLocation":null,"outcome":null,"possession":92,"xg":null},{"id":"4bd0f3a6-85fb-4f44-a71a-79d3d7e8c970","index":2023,"period":2,"minute":57,"second":15,"timestamp":"00:12:15.524","team":"Bolivia","player":"Boris Cespedes","type":"Pressure","location":[67.9,60.4],"endLocation":null,"outcome":null,"possession":93,"xg":null},{"id":"bdfc9eed-0e25-4104-adab-f2ea9bb6b9a0","index":2027,"period":2,"minute":57,"second":17,"timestamp":"00:12:17.369","team":"Bolivia","player":"Yomar Rene Rocha Rodriguez","type":"Pressure","location":[63.3,72.1],"endLocation":null,"outcome":null,"possession":93,"xg":null},{"id":"79329613-b55b-41ef-be63-74faf2cb7d11","index":2029,"period":2,"minute":57,"second":18,"timestamp":"00:12:18.769","team":"Bolivia","player":"Héctor Manuel Cuellar Rosales","type":"Pressure","location":[49.5,74.6],"endLocation":null,"outcome":null,"possession":93,"xg":null},{"id":"20345e5b-fba0-492f-b234-87d6c15a8ad0","index":2036,"period":2,"minute":57,"second":32,"timestamp":"00:12:32.537","team":"Panama","player":"José Fajardo Nelson","type":"Pressure","location":[82.3,26.3],"endLocation":null,"outcome":null,"possession":94,"xg":null},{"id":"193317e2-912b-4dd6-b17b-3df7a3bd599a","index":2061,"period":2,"minute":58,"second":1,"timestamp":"00:13:01.327","team":"Panama","player":"José Fajardo Nelson","type":"Pressure","location":[62.6,48.5],"endLocation":null,"outcome":null,"possession":94,"xg":null},{"id":"7d4130df-ec20-41f1-8755-cfd3304a6a81","index":2065,"period":2,"minute":58,"second":5,"timestamp":"00:13:05.977","team":"Bolivia","player":"Ramiro Vaca Ponce","type":"Pressure","location":[96.6,8.9],"endLocation":null,"outcome":null,"possession":94,"xg":null},{"id":"7b8e411c-25ed-46b7-a749-94cfa84a0be5","index":2112,"period":2,"minute":59,"second":27,"timestamp":"00:14:27.253","team":"Bolivia","player":"Héctor Manuel Cuellar Rosales","type":"Pressure","location":[15.3,71.9],"endLocation":null,"outcome":null,"possession":97,"xg":null},{"id":"07b5b735-1724-4d8b-83e5-5a825e34460f","index":2128,"period":2,"minute":60,"second":55,"timestamp":"00:15:55.691","team":"Bolivia","player":"Gabriel Alejandro Villamíl Cortéz","type":"Pressure","location":[32,32.3],"endLocation":null,"outcome":null,"possession":98,"xg":null},{"id":"7751332e-735e-45a4-9ad8-a6b095b3f3ad","index":2139,"period":2,"minute":61,"second":9,"timestamp":"00:16:09.101","team":"Panama","player":"Edgardo Isaac Fariña Wynter","type":"Pressure","location":[99.9,57.8],"endLocation":null,"outcome":null,"possession":98,"xg":null},{"id":"f469a727-bd90-4892-a907-f5e718c6a14a","index":2155,"period":2,"minute":61,"second":39,"timestamp":"00:16:39.740","team":"Bolivia","player":"Ramiro Vaca Ponce","type":"Pressure","location":[49.8,11.8],"endLocation":null,"outcome":null,"possession":99,"xg":null},{"id":"b9087e30-552d-4aef-b472-24ac35fc1e35","index":2156,"period":2,"minute":61,"second":41,"timestamp":"00:16:41.608","team":"Bolivia","player":"Gabriel Alejandro Villamíl Cortéz","type":"Pressure","location":[32.3,19],"endLocation":null,"outcome":null,"possession":99,"xg":null},{"id":"d69bb945-2762-46c4-8d4a-4730b103db85","index":2160,"period":2,"minute":61,"second":43,"timestamp":"00:16:43.702","team":"Bolivia","player":"José Manuel Sagredo Chávez","type":"Pressure","location":[23,6.6],"endLocation":null,"outcome":null,"possession":99,"xg":null},{"id":"1771f1f7-94b7-43db-9b84-41da801cffa1","index":2186,"period":2,"minute":63,"second":26,"timestamp":"00:18:26.633","team":"Panama","player":"Cristian Jesús Martínez","type":"Pressure","location":[55,42.8],"endLocation":null,"outcome":null,"possession":101,"xg":null},{"id":"83f50250-7957-41cd-8122-ec65b30c773b","index":2195,"period":2,"minute":63,"second":33,"timestamp":"00:18:33.639","team":"Panama","player":"Cristian Jesús Martínez","type":"Pressure","location":[57.8,66.6],"endLocation":null,"outcome":null,"possession":101,"xg":null},{"id":"966af604-7c5e-41bb-9edb-a9652bc3a669","index":2213,"period":2,"minute":63,"second":49,"timestamp":"00:18:49.934","team":"Panama","player":"Edgar Yoel Bárcenas Herrera","type":"Pressure","location":[49,7.4],"endLocation":null,"outcome":null,"possession":101,"xg":null},{"id":"aaeee950-60c3-4b2d-8987-1399de1f362d","index":2227,"period":2,"minute":64,"second":0,"timestamp":"00:19:00.050","team":"Bolivia","player":"Bruno Miranda Villagomez","type":"Pressure","location":[110,41.5],"endLocation":null,"outcome":null,"possession":102,"xg":null},{"id":"78465785-6450-4576-874e-0bddc69b05d3","index":2233,"period":2,"minute":64,"second":8,"timestamp":"00:19:08.190","team":"Bolivia","player":"Luis Fernando Haquín Lopez","type":"Pressure","location":[33.6,31.5],"endLocation":null,"outcome":null,"possession":102,"xg":null},{"id":"8071d7ef-ebeb-4d71-bece-c22b3419e26a","index":2244,"period":2,"minute":64,"second":26,"timestamp":"00:19:26.529","team":"Panama","player":"Kahiser Lenis Navarro","type":"Pressure","location":[70.3,77.1],"endLocation":null,"outcome":null,"possession":103,"xg":null},{"id":"f07ea5ac-89eb-4a20-844c-a613b89008e0","index":2258,"period":2,"minute":64,"second":56,"timestamp":"00:19:56.451","team":"Bolivia","player":"Marcelo Sebastián Suárez Justiniano","type":"Pressure","location":[44.3,16.4],"endLocation":null,"outcome":null,"possession":104,"xg":null},{"id":"071d9a7a-aef2-4249-80c4-c91d23ea77bf","index":2293,"period":2,"minute":66,"second":11,"timestamp":"00:21:11.862","team":"Panama","player":"José Fajardo Nelson","type":"Pressure","location":[93,36.5],"endLocation":null,"outcome":null,"possession":106,"xg":null},{"id":"c3835727-eefd-4a2a-86a4-108621b2b680","index":2300,"period":2,"minute":66,"second":18,"timestamp":"00:21:18.551","team":"Panama","player":"Cristian Jesús Martínez","type":"Pressure","location":[73.3,33.2],"endLocation":null,"outcome":null,"possession":106,"xg":null},{"id":"38a8f825-4682-4f11-b9ff-4725d1951338","index":2307,"period":2,"minute":66,"second":24,"timestamp":"00:21:24.272","team":"Panama","player":"Cristian Jesús Martínez","type":"Pressure","location":[86.9,18.3],"endLocation":null,"outcome":null,"possession":106,"xg":null},{"id":"5d1a283b-a09d-4afd-b597-1e3575c9e581","index":2311,"period":2,"minute":66,"second":26,"timestamp":"00:21:26.340","team":"Bolivia","player":"Leonel Justiniano Arauz","type":"Pressure","location":[20,58.7],"endLocation":null,"outcome":null,"possession":106,"xg":null},{"id":"c5efd1c6-9756-4841-9d42-94be99e80612","index":2316,"period":2,"minute":66,"second":30,"timestamp":"00:21:30.138","team":"Bolivia","player":"Adalid Terrazas Abasto","type":"Pressure","location":[11.8,32.1],"endLocation":null,"outcome":null,"possession":107,"xg":null},{"id":"b6734ef5-bf89-40cc-81fe-21cd16c3da2d","index":2329,"period":2,"minute":66,"second":37,"timestamp":"00:21:37.415","team":"Panama","player":"Kahiser Lenis Navarro","type":"Pressure","location":[114.6,66],"endLocation":null,"outcome":null,"possession":108,"xg":null},{"id":"80d26818-c706-4b90-b202-a6b26b0daeb3","index":2333,"period":2,"minute":66,"second":42,"timestamp":"00:21:42.031","team":"Panama","player":"Kahiser Lenis Navarro","type":"Pressure","location":[87.3,77],"endLocation":null,"outcome":null,"possession":108,"xg":null},{"id":"0bf5717f-3db4-47cc-be78-a5efdc034bce","index":2358,"period":2,"minute":67,"second":12,"timestamp":"00:22:12.083","team":"Panama","player":"César Rodolfo Blackman Camarena","type":"Pressure","location":[44.3,76.7],"endLocation":null,"outcome":null,"possession":108,"xg":null},{"id":"3779206c-f86f-481f-aa97-86bab5fdc069","index":2360,"period":2,"minute":67,"second":13,"timestamp":"00:22:13.596","team":"Panama","player":"Kahiser Lenis Navarro","type":"Pressure","location":[52.5,76.1],"endLocation":null,"outcome":null,"possession":108,"xg":null},{"id":"c99aad22-4ce5-4a38-bd0d-20e19b58b1a7","index":2366,"period":2,"minute":67,"second":15,"timestamp":"00:22:15.327","team":"Panama","player":"Jovani Francisco Welch Lopez","type":"Pressure","location":[54.5,66.4],"endLocation":null,"outcome":null,"possession":108,"xg":null},{"id":"1dac21a9-c49c-4733-b900-f33061ed2cef","index":2372,"period":2,"minute":67,"second":19,"timestamp":"00:22:19.577","team":"Bolivia","player":"Adalid Terrazas Abasto","type":"Pressure","location":[51.4,11.7],"endLocation":null,"outcome":null,"possession":108,"xg":null},{"id":"d22e63a4-60bc-4861-8263-9dd643f88cbe","index":2383,"period":2,"minute":67,"second":32,"timestamp":"00:22:32.204","team":"Panama","player":"Carlos Miguel Harvey Cesneros","type":"Pressure","location":[28.2,41.5],"endLocation":null,"outcome":null,"possession":108,"xg":null},{"id":"0e504cdd-83e5-411c-a18d-43d2252dc318","index":2388,"period":2,"minute":67,"second":34,"timestamp":"00:22:34.863","team":"Panama","player":"César Rodolfo Blackman Camarena","type":"Pressure","location":[26.2,53.1],"endLocation":null,"outcome":null,"possession":108,"xg":null},{"id":"97473a28-178e-47c2-a4c5-01a03e1f6ed3","index":2395,"period":2,"minute":67,"second":39,"timestamp":"00:22:39.353","team":"Bolivia","player":"Miguel Ángel Terceros","type":"Pressure","location":[88.4,42.1],"endLocation":null,"outcome":null,"possession":108,"xg":null},{"id":"f7d9e16c-e278-4c4f-b343-938ca5503ec6","index":2400,"period":2,"minute":67,"second":43,"timestamp":"00:22:43.925","team":"Panama","player":"Erick Javier Davis Grajales","type":"Pressure","location":[62.5,11],"endLocation":null,"outcome":null,"possession":108,"xg":null},{"id":"3cd46c01-2cf5-4200-86ef-39fc3ae39ffe","index":2404,"period":2,"minute":67,"second":48,"timestamp":"00:22:48.614","team":"Panama","player":"Cristian Jesús Martínez","type":"Pressure","location":[68.3,20.5],"endLocation":null,"outcome":null,"possession":108,"xg":null},{"id":"fd3123d4-8477-4998-9f92-07af4a0dca3b","index":2426,"period":2,"minute":68,"second":9,"timestamp":"00:23:09.353","team":"Panama","player":"Carlos Miguel Harvey Cesneros","type":"Pressure","location":[26,39.5],"endLocation":null,"outcome":null,"possession":108,"xg":null},{"id":"6c27bf1c-28de-444d-9138-e0160deea95c","index":2433,"period":2,"minute":68,"second":11,"timestamp":"00:23:11.936","team":"Panama","player":"José Ángel Córdoba Chambers","type":"Pressure","location":[18.6,41.1],"endLocation":null,"outcome":null,"possession":108,"xg":null},{"id":"ca4849a1-0fdc-4500-8cec-4428834f566c","index":2460,"period":2,"minute":70,"second":53,"timestamp":"00:25:53.374","team":"Bolivia","player":"Bruno Miranda Villagomez","type":"Pressure","location":[110.8,39.2],"endLocation":null,"outcome":null,"possession":109,"xg":null},{"id":"8c7be89b-12e1-4099-b937-e896c9151401","index":2482,"period":2,"minute":71,"second":27,"timestamp":"00:26:27.988","team":"Panama","player":"Edgar Yoel Bárcenas Herrera","type":"Pressure","location":[96.4,18.1],"endLocation":null,"outcome":null,"possession":111,"xg":null},{"id":"dcf45fa5-7679-4d93-89d8-dba2818ad581","index":2483,"period":2,"minute":71,"second":29,"timestamp":"00:26:29.915","team":"Panama","player":"Edgar Yoel Bárcenas Herrera","type":"Pressure","location":[96.6,14.3],"endLocation":null,"outcome":null,"possession":111,"xg":null},{"id":"717ce0eb-5f1d-46f1-9d35-46bbcc2fde54","index":2489,"period":2,"minute":71,"second":33,"timestamp":"00:26:33.302","team":"Panama","player":"José Fajardo Nelson","type":"Pressure","location":[83.3,41.5],"endLocation":null,"outcome":null,"possession":111,"xg":null},{"id":"fed02f18-d0ed-4196-aaa5-c924ff2db565","index":2496,"period":2,"minute":71,"second":37,"timestamp":"00:26:37.056","team":"Panama","player":"Kahiser Lenis Navarro","type":"Pressure","location":[97,54.6],"endLocation":null,"outcome":null,"possession":111,"xg":null},{"id":"c1b43ed4-2b77-4152-8c75-5f4fce7581cb","index":2500,"period":2,"minute":71,"second":39,"timestamp":"00:26:39.078","team":"Panama","player":"Jovani Francisco Welch Lopez","type":"Pressure","location":[88.2,52.4],"endLocation":null,"outcome":null,"possession":111,"xg":null},{"id":"50ff0627-4d9d-40fa-8e7a-0aec75547afa","index":2504,"period":2,"minute":71,"second":40,"timestamp":"00:26:40.779","team":"Panama","player":"Jovani Francisco Welch Lopez","type":"Pressure","location":[97.9,54],"endLocation":null,"outcome":null,"possession":111,"xg":null},{"id":"eee84c4e-7a84-4abe-a46b-8b8223ec8e63","index":2513,"period":2,"minute":71,"second":45,"timestamp":"00:26:45.569","team":"Panama","player":"César Rodolfo Blackman Camarena","type":"Pressure","location":[75.1,75.9],"endLocation":null,"outcome":null,"possession":111,"xg":null},{"id":"d64bfd4a-f7c6-4380-8702-2c11c77928f3","index":2525,"period":2,"minute":71,"second":57,"timestamp":"00:26:57.260","team":"Panama","player":"José Fajardo Nelson","type":"Pressure","location":[86.7,61.7],"endLocation":null,"outcome":null,"possession":111,"xg":null},{"id":"89218a85-4bc3-4104-8584-d73c47d24b08","index":2529,"period":2,"minute":72,"second":0,"timestamp":"00:27:00.919","team":"Panama","player":"José Fajardo Nelson","type":"Pressure","location":[109.4,46.4],"endLocation":null,"outcome":null,"possession":111,"xg":null},{"id":"1377298b-0f8c-43ad-83f6-4eb8faea6670","index":2542,"period":2,"minute":72,"second":14,"timestamp":"00:27:14.304","team":"Bolivia","player":"Marcelo Sebastián Suárez Justiniano","type":"Pressure","location":[12.2,40.3],"endLocation":null,"outcome":null,"possession":112,"xg":null},{"id":"07acf80c-9d5d-4257-a3c9-9ab376cf431b","index":2547,"period":2,"minute":72,"second":17,"timestamp":"00:27:17.377","team":"Bolivia","player":"José Manuel Sagredo Chávez","type":"Pressure","location":[31.5,28.7],"endLocation":null,"outcome":null,"possession":112,"xg":null},{"id":"407cffb4-03c6-4c16-8f30-93624b8466c2","index":2553,"period":2,"minute":72,"second":19,"timestamp":"00:27:19.049","team":"Bolivia","player":"Luis Fernando Haquín Lopez","type":"Pressure","location":[26.9,36.3],"endLocation":null,"outcome":null,"possession":112,"xg":null},{"id":"dc548dfc-a7a8-4ced-8aff-fcfdd5bcdaee","index":2554,"period":2,"minute":72,"second":19,"timestamp":"00:27:19.937","team":"Bolivia","player":"José Manuel Sagredo Chávez","type":"Pressure","location":[29,32.3],"endLocation":null,"outcome":null,"possession":112,"xg":null},{"id":"85add832-fab2-4db8-b163-4fc54acb540b","index":2558,"period":2,"minute":72,"second":21,"timestamp":"00:27:21.028","team":"Bolivia","player":"Carmelo Algarañaz Añez","type":"Pressure","location":[26.9,25.2],"endLocation":null,"outcome":null,"possession":112,"xg":null},{"id":"6f9e20b6-3f05-4d8f-a886-8aac013600bb","index":2572,"period":2,"minute":74,"second":0,"timestamp":"00:29:00.327","team":"Bolivia","player":"Miguel Ángel Terceros","type":"Pressure","location":[76.3,24.6],"endLocation":null,"outcome":null,"possession":114,"xg":null},{"id":"311419b6-25d4-44fa-9753-b6177f50d0c4","index":2576,"period":2,"minute":74,"second":1,"timestamp":"00:29:01.450","team":"Panama","player":"Jovani Francisco Welch Lopez","type":"Pressure","location":[38.8,53.1],"endLocation":null,"outcome":null,"possession":114,"xg":null},{"id":"5dff6d22-4688-4c1c-a1db-a133112881a2","index":2577,"period":2,"minute":74,"second":1,"timestamp":"00:29:01.452","team":"Panama","player":"Abdiel Armando Ayarza Cocanegra","type":"Pressure","location":[37.7,51.8],"endLocation":null,"outcome":null,"possession":114,"xg":null},{"id":"607701a4-d62b-4f1a-8486-8b4b10bdda8f","index":2582,"period":2,"minute":74,"second":4,"timestamp":"00:29:04.558","team":"Bolivia","player":"Miguel Ángel Terceros","type":"Pressure","location":[80,20],"endLocation":null,"outcome":null,"possession":114,"xg":null},{"id":"c7ac9565-4836-4284-9bd9-e78a50c73fe1","index":2584,"period":2,"minute":74,"second":5,"timestamp":"00:29:05.755","team":"Bolivia","player":"Adalid Terrazas Abasto","type":"Pressure","location":[68.2,8.7],"endLocation":null,"outcome":null,"possession":114,"xg":null},{"id":"fb363b4b-2302-4f66-ab4e-79fed7ce38cc","index":2607,"period":2,"minute":74,"second":28,"timestamp":"00:29:28.860","team":"Panama","player":"Edgar Yoel Bárcenas Herrera","type":"Pressure","location":[81.1,38.2],"endLocation":null,"outcome":null,"possession":115,"xg":null},{"id":"ae433bc0-ea3a-4eec-9dd5-3d681700ae1e","index":2611,"period":2,"minute":74,"second":31,"timestamp":"00:29:31.390","team":"Panama","player":"Edgar Yoel Bárcenas Herrera","type":"Pressure","location":[76.8,53.3],"endLocation":null,"outcome":null,"possession":115,"xg":null},{"id":"2bb289f0-d87d-4b73-ad9a-cdcaec2e7114","index":2613,"period":2,"minute":74,"second":33,"timestamp":"00:29:33.414","team":"Panama","player":"José Fajardo Nelson","type":"Pressure","location":[87.5,47.1],"endLocation":null,"outcome":null,"possession":115,"xg":null},{"id":"caf21f66-e9d1-463f-a081-799cf7cd6cff","index":2623,"period":2,"minute":74,"second":37,"timestamp":"00:29:37.216","team":"Panama","player":"Jovani Francisco Welch Lopez","type":"Pressure","location":[67.3,53.5],"endLocation":null,"outcome":null,"possession":115,"xg":null},{"id":"4ce66efa-2478-46f3-a578-aae7dfa2edbc","index":2633,"period":2,"minute":74,"second":47,"timestamp":"00:29:47.751","team":"Panama","player":"Abdiel Armando Ayarza Cocanegra","type":"Pressure","location":[19.7,40.9],"endLocation":null,"outcome":null,"possession":115,"xg":null},{"id":"4e2d1c0d-bf1a-45bc-a50b-e2b8c8a7cb80","index":2639,"period":2,"minute":74,"second":58,"timestamp":"00:29:58.320","team":"Bolivia","player":"Héctor Manuel Cuellar Rosales","type":"Pressure","location":[56.1,69.5],"endLocation":null,"outcome":null,"possession":117,"xg":null},{"id":"b9550b22-0c63-46b7-89d8-1b02dfc3fe37","index":2651,"period":2,"minute":75,"second":15,"timestamp":"00:30:15.487","team":"Panama","player":"José Fajardo Nelson","type":"Pressure","location":[85.9,54.4],"endLocation":null,"outcome":null,"possession":118,"xg":null},{"id":"06929242-aa43-4a3f-9874-bcd799794288","index":2656,"period":2,"minute":75,"second":18,"timestamp":"00:30:18.024","team":"Panama","player":"Jovani Francisco Welch Lopez","type":"Pressure","location":[71.5,46.9],"endLocation":null,"outcome":null,"possession":119,"xg":null},{"id":"8bad3d45-c01f-4c76-ae55-05f288c1d1fb","index":2663,"period":2,"minute":75,"second":23,"timestamp":"00:30:23.365","team":"Panama","player":"Abdiel Armando Ayarza Cocanegra","type":"Pressure","location":[70.3,50.4],"endLocation":null,"outcome":null,"possession":119,"xg":null},{"id":"c429f816-9c10-47f4-b7f5-6393df98b4b4","index":2683,"period":2,"minute":75,"second":43,"timestamp":"00:30:43.475","team":"Bolivia","player":"Miguel Ángel Terceros","type":"Pressure","location":[107,48.5],"endLocation":null,"outcome":null,"possession":119,"xg":null},{"id":"5426870a-aa56-42c3-b51e-1756850db938","index":2688,"period":2,"minute":75,"second":45,"timestamp":"00:30:45.990","team":"Bolivia","player":"Bruno Miranda Villagomez","type":"Pressure","location":[100.8,62.7],"endLocation":null,"outcome":null,"possession":120,"xg":null},{"id":"ff51974f-133b-4508-82b5-0ad1b837ab87","index":2691,"period":2,"minute":75,"second":47,"timestamp":"00:30:47.313","team":"Bolivia","player":"Miguel Ángel Terceros","type":"Pressure","location":[103.4,60.3],"endLocation":null,"outcome":null,"possession":120,"xg":null},{"id":"d14e0167-ed43-4eba-9d5e-23f46fb790d0","index":2695,"period":2,"minute":75,"second":49,"timestamp":"00:30:49.908","team":"Bolivia","player":"Ramiro Vaca Ponce","type":"Pressure","location":[100.1,55.4],"endLocation":null,"outcome":null,"possession":120,"xg":null},{"id":"3d799a13-b501-4d48-8052-32c48b3bb36d","index":2710,"period":2,"minute":76,"second":40,"timestamp":"00:31:40.967","team":"Bolivia","player":"Leonel Justiniano Arauz","type":"Pressure","location":[63.1,54.4],"endLocation":null,"outcome":null,"possession":121,"xg":null},{"id":"0b3be54b-de61-45bb-bbcf-9d015aacb4a0","index":2730,"period":2,"minute":77,"second":7,"timestamp":"00:32:07.452","team":"Panama","player":"Eduardo Antonio Guerrero Lozcano","type":"Pressure","location":[88.2,18.3],"endLocation":null,"outcome":null,"possession":122,"xg":null},{"id":"364cd3ab-09c9-4ec5-840e-a3e8f13f32a0","index":2740,"period":2,"minute":77,"second":17,"timestamp":"00:32:17.939","team":"Bolivia","player":"Miguel Ángel Terceros","type":"Pressure","location":[111.3,72.2],"endLocation":null,"outcome":null,"possession":122,"xg":null},{"id":"88101277-1249-4b10-84c9-0d04e310d3a8","index":2743,"period":2,"minute":77,"second":39,"timestamp":"00:32:39.271","team":"Panama","player":"José Fajardo Nelson","type":"Pressure","location":[59,9.9],"endLocation":null,"outcome":null,"possession":123,"xg":null},{"id":"11fc8291-5899-41e5-a441-6f9dbcb83f06","index":2790,"period":2,"minute":80,"second":5,"timestamp":"00:35:05.652","team":"Panama","player":"Jovani Francisco Welch Lopez","type":"Pressure","location":[39.2,21.9],"endLocation":null,"outcome":null,"possession":125,"xg":null},{"id":"3113e673-312c-48a4-bb64-d79851762e1d","index":2796,"period":2,"minute":80,"second":10,"timestamp":"00:35:10.503","team":"Panama","player":"Erick Javier Davis Grajales","type":"Pressure","location":[21.7,7.5],"endLocation":null,"outcome":null,"possession":125,"xg":null},{"id":"13782ac4-bf5e-456e-87d6-de3e2294db2c","index":2818,"period":2,"minute":80,"second":47,"timestamp":"00:35:47.130","team":"Panama","player":"César Rodolfo Blackman Camarena","type":"Pressure","location":[3.6,64.8],"endLocation":null,"outcome":null,"possession":126,"xg":null},{"id":"921449bd-0bdb-486a-824a-5b578db88411","index":2831,"period":2,"minute":81,"second":41,"timestamp":"00:36:41.055","team":"Bolivia","player":"Leonel Justiniano Arauz","type":"Pressure","location":[29.9,56.7],"endLocation":null,"outcome":null,"possession":127,"xg":null},{"id":"5fed954e-5da8-4ed5-b9ea-22a79e35de25","index":2848,"period":2,"minute":82,"second":3,"timestamp":"00:37:03.301","team":"Bolivia","player":"Bruno Miranda Villagomez","type":"Pressure","location":[56.9,14.6],"endLocation":null,"outcome":null,"possession":127,"xg":null},{"id":"1c3bf7a9-c7af-417f-ba90-3a2f1818bad7","index":2855,"period":2,"minute":82,"second":10,"timestamp":"00:37:10.277","team":"Panama","player":"Abdiel Armando Ayarza Cocanegra","type":"Pressure","location":[70.7,49.1],"endLocation":null,"outcome":null,"possession":128,"xg":null},{"id":"8a9a3872-286a-43c0-924d-9a050d1c9255","index":2880,"period":2,"minute":84,"second":41,"timestamp":"00:39:41.141","team":"Bolivia","player":"José Manuel Sagredo Chávez","type":"Pressure","location":[33,19.8],"endLocation":null,"outcome":null,"possession":130,"xg":null},{"id":"854be53f-54a0-40df-a51d-63009d0b80d6","index":2892,"period":2,"minute":84,"second":50,"timestamp":"00:39:50.765","team":"Bolivia","player":"Adalid Terrazas Abasto","type":"Pressure","location":[36.2,33.7],"endLocation":null,"outcome":null,"possession":130,"xg":null},{"id":"7eb779f4-b31a-4fda-931d-8b3174289fd1","index":2896,"period":2,"minute":84,"second":52,"timestamp":"00:39:52.506","team":"Bolivia","player":"Adalid Terrazas Abasto","type":"Pressure","location":[41.5,25],"endLocation":null,"outcome":null,"possession":130,"xg":null},{"id":"1c01e2b6-811f-4f6c-b9d6-3c2bb9400071","index":2934,"period":2,"minute":86,"second":37,"timestamp":"00:41:37.381","team":"Bolivia","player":"Leonel Justiniano Arauz","type":"Pressure","location":[85.8,38.2],"endLocation":null,"outcome":null,"possession":133,"xg":null},{"id":"6dcb38ca-e85b-4490-a73e-6df71139848d","index":2940,"period":2,"minute":86,"second":43,"timestamp":"00:41:43.114","team":"Bolivia","player":"Lucas Leónidas Chávez Cruz","type":"Pressure","location":[98.4,64.5],"endLocation":null,"outcome":null,"possession":133,"xg":null},{"id":"e12a8263-7f94-4c00-89b5-ef56b4e4f100","index":2951,"period":2,"minute":86,"second":54,"timestamp":"00:41:54.704","team":"Panama","player":"Edgar Yoel Bárcenas Herrera","type":"Pressure","location":[72.9,57.9],"endLocation":null,"outcome":null,"possession":134,"xg":null},{"id":"f75b2061-d356-4d50-b4ef-5e432186c504","index":2957,"period":2,"minute":87,"second":3,"timestamp":"00:42:03.817","team":"Panama","player":"Freddy Elías Góndola Smith","type":"Pressure","location":[39.6,6.9],"endLocation":null,"outcome":null,"possession":134,"xg":null},{"id":"17bb7210-d4c7-4020-a55e-5718d708cec0","index":2960,"period":2,"minute":87,"second":6,"timestamp":"00:42:06.163","team":"Panama","player":"Freddy Elías Góndola Smith","type":"Pressure","location":[38.1,5.1],"endLocation":null,"outcome":null,"possession":134,"xg":null},{"id":"6620edd6-9bc1-41af-8a51-ceec112d99a4","index":2966,"period":2,"minute":87,"second":8,"timestamp":"00:42:08.660","team":"Panama","player":"Eduardo Antonio Guerrero Lozcano","type":"Pressure","location":[51.3,9.7],"endLocation":null,"outcome":null,"possession":134,"xg":null},{"id":"9faafd6e-1a41-4f36-a559-dc31bbcc8315","index":2971,"period":2,"minute":87,"second":13,"timestamp":"00:42:13.451","team":"Panama","player":"Jovani Francisco Welch Lopez","type":"Pressure","location":[28.4,9.7],"endLocation":null,"outcome":null,"possession":134,"xg":null},{"id":"225149c1-bf93-4b1b-9709-09c83c6567fd","index":2974,"period":2,"minute":87,"second":15,"timestamp":"00:42:15.838","team":"Panama","player":"Erick Javier Davis Grajales","type":"Pressure","location":[15.7,6.5],"endLocation":null,"outcome":null,"possession":134,"xg":null},{"id":"23f4cf42-6379-4448-b97e-9f023852bf47","index":3050,"period":2,"minute":90,"second":9,"timestamp":"00:45:09.475","team":"Bolivia","player":"Marcelo Sebastián Suárez Justiniano","type":"Pressure","location":[15.6,38.6],"endLocation":null,"outcome":null,"possession":136,"xg":null},{"id":"fc47b714-714e-46e7-9772-6ad94dcef950","index":3074,"period":2,"minute":91,"second":55,"timestamp":"00:46:55.806","team":"Bolivia","player":"Adalid Terrazas Abasto","type":"Pressure","location":[95.3,11.5],"endLocation":null,"outcome":null,"possession":137,"xg":null},{"id":"f5a6e1f9-ffa6-4c4f-8d15-ae7fa79c9cd6","index":3089,"period":2,"minute":92,"second":16,"timestamp":"00:47:16.287","team":"Panama","player":"Abdiel Armando Ayarza Cocanegra","type":"Pressure","location":[50.1,60.3],"endLocation":null,"outcome":null,"possession":138,"xg":null},{"id":"a8749f4f-b0ed-4ca7-87b7-b5c5aebf9019","index":3103,"period":2,"minute":92,"second":30,"timestamp":"00:47:30.084","team":"Panama","player":"Freddy Elías Góndola Smith","type":"Pressure","location":[50.3,7.9],"endLocation":null,"outcome":null,"possession":138,"xg":null},{"id":"7bbf4178-f9eb-4117-b275-d3e30dd3e80e","index":3105,"period":2,"minute":92,"second":32,"timestamp":"00:47:32.248","team":"Panama","player":"Freddy Elías Góndola Smith","type":"Pressure","location":[68.3,16.8],"endLocation":null,"outcome":null,"possession":138,"xg":null},{"id":"65a743a0-6a58-448a-9181-d240a76e8c49","index":3118,"period":2,"minute":92,"second":37,"timestamp":"00:47:37.490","team":"Panama","player":"Abdiel Armando Ayarza Cocanegra","type":"Pressure","location":[64,25.3],"endLocation":null,"outcome":null,"possession":138,"xg":null},{"id":"699c7a81-7d8d-48bf-92e3-f60031164cbc","index":3122,"period":2,"minute":92,"second":39,"timestamp":"00:47:39.015","team":"Bolivia","player":"Adalid Terrazas Abasto","type":"Pressure","location":[55.9,57.6],"endLocation":null,"outcome":null,"possession":139,"xg":null},{"id":"acac7953-5785-4c37-a6af-d6e298217a69","index":3130,"period":2,"minute":92,"second":43,"timestamp":"00:47:43.722","team":"Bolivia","player":"Leonel Justiniano Arauz","type":"Pressure","location":[53.4,39.2],"endLocation":null,"outcome":null,"possession":139,"xg":null},{"id":"0df84755-f8c9-4e61-b070-3665a86216b7","index":3131,"period":2,"minute":92,"second":44,"timestamp":"00:47:44.595","team":"Bolivia","player":"Fernando Javier Saucedo Pereyra","type":"Pressure","location":[55.9,41.8],"endLocation":null,"outcome":null,"possession":139,"xg":null},{"id":"6406a447-bf0a-400d-bd93-420cf431d5dd","index":3135,"period":2,"minute":92,"second":46,"timestamp":"00:47:46.357","team":"Bolivia","player":"Adalid Terrazas Abasto","type":"Pressure","location":[56.3,41.6],"endLocation":null,"outcome":null,"possession":139,"xg":null},{"id":"8ad90778-3e0d-4611-9d02-f335f2f1d27e","index":3139,"period":2,"minute":92,"second":49,"timestamp":"00:47:49.531","team":"Bolivia","player":"Adalid Terrazas Abasto","type":"Pressure","location":[67.6,33.2],"endLocation":null,"outcome":null,"possession":139,"xg":null},{"id":"725bf364-5ae7-4c86-9a2d-ec0fb7231b32","index":3140,"period":2,"minute":92,"second":49,"timestamp":"00:47:49.603","team":"Bolivia","player":"Bruno Miranda Villagomez","type":"Pressure","location":[68.8,34.3],"endLocation":null,"outcome":null,"possession":139,"xg":null},{"id":"e69662b9-fc9f-4353-b3c9-f894a6ea40ce","index":3144,"period":2,"minute":92,"second":52,"timestamp":"00:47:52.951","team":"Bolivia","player":"Fernando Javier Saucedo Pereyra","type":"Pressure","location":[47.4,28.3],"endLocation":null,"outcome":null,"possession":139,"xg":null},{"id":"4496dd82-dd3a-4933-a647-ae0d04b4e135","index":3157,"period":2,"minute":93,"second":28,"timestamp":"00:48:28.176","team":"Bolivia","player":"Leonel Justiniano Arauz","type":"Pressure","location":[44.5,61.3],"endLocation":null,"outcome":null,"possession":140,"xg":null},{"id":"0a55d0ca-fee9-4284-8a61-415b86179e5d","index":3168,"period":2,"minute":93,"second":36,"timestamp":"00:48:36.534","team":"Bolivia","player":"Fernando Javier Saucedo Pereyra","type":"Pressure","location":[105.9,36.1],"endLocation":null,"outcome":null,"possession":140,"xg":null},{"id":"85e13c7d-4bbc-43e4-9d75-8213bb1a7bf8","index":3177,"period":2,"minute":93,"second":45,"timestamp":"00:48:45.717","team":"Bolivia","player":"Adalid Terrazas Abasto","type":"Pressure","location":[55,35.2],"endLocation":null,"outcome":null,"possession":140,"xg":null},{"id":"1c7333a5-fdee-4809-8365-f838fe1444d5","index":3183,"period":2,"minute":93,"second":49,"timestamp":"00:48:49.203","team":"Bolivia","player":"Lucas Leónidas Chávez Cruz","type":"Pressure","location":[55.8,31],"endLocation":null,"outcome":null,"possession":140,"xg":null},{"id":"252a362e-4ab2-4f37-813a-34e5543a321d","index":3190,"period":2,"minute":93,"second":55,"timestamp":"00:48:55.631","team":"Bolivia","player":"Carmelo Algarañaz Añez","type":"Pressure","location":[27.7,13.5],"endLocation":null,"outcome":null,"possession":140,"xg":null},{"id":"13021eef-faa1-4038-b308-08d447645400","index":3191,"period":2,"minute":93,"second":58,"timestamp":"00:48:58.379","team":"Bolivia","player":"José Manuel Sagredo Chávez","type":"Pressure","location":[15,5.3],"endLocation":null,"outcome":null,"possession":140,"xg":null},{"id":"6495de99-3cb6-4077-9428-898dcecc9785","index":3196,"period":2,"minute":94,"second":0,"timestamp":"00:49:00.405","team":"Panama","player":"Kahiser Lenis Navarro","type":"Pressure","location":[107.9,77.7],"endLocation":null,"outcome":null,"possession":140,"xg":null},{"id":"f7c282fe-b30a-4aff-93a2-68af9e6f114a","index":3197,"period":2,"minute":94,"second":1,"timestamp":"00:49:01.766","team":"Panama","player":"Abdiel Armando Ayarza Cocanegra","type":"Pressure","location":[105.9,76.7],"endLocation":null,"outcome":null,"possession":140,"xg":null},{"id":"461a3853-971c-4b59-bc04-d587827651f0","index":3201,"period":2,"minute":94,"second":4,"timestamp":"00:49:04.746","team":"Bolivia","player":"Carmelo Algarañaz Añez","type":"Pressure","location":[4.3,2.8],"endLocation":null,"outcome":null,"possession":140,"xg":null},{"id":"c9cdcc33-1333-421f-b3cd-d2767bd56489","index":3205,"period":2,"minute":94,"second":26,"timestamp":"00:49:26.678","team":"Bolivia","player":"José Manuel Sagredo Chávez","type":"Pressure","location":[2.3,5.3],"endLocation":null,"outcome":null,"possession":141,"xg":null},{"id":"3219da93-71a0-48f6-a76f-ac81e62022de","index":3211,"period":2,"minute":94,"second":30,"timestamp":"00:49:30.758","team":"Bolivia","player":"José Manuel Sagredo Chávez","type":"Pressure","location":[4.7,13.5],"endLocation":null,"outcome":null,"possession":141,"xg":null},{"id":"fb12756d-76b6-4395-95ce-d576ca7d84a7","index":3212,"period":2,"minute":94,"second":30,"timestamp":"00:49:30.830","team":"Bolivia","player":"Luis Fernando Haquín Lopez","type":"Pressure","location":[4.9,12.7],"endLocation":null,"outcome":null,"possession":141,"xg":null},{"id":"48150ea2-05e0-4a6c-9a17-d82fadfc92f9","index":3233,"period":2,"minute":94,"second":52,"timestamp":"00:49:52.556","team":"Panama","player":"Edgar Yoel Bárcenas Herrera","type":"Pressure","location":[15.9,68.4],"endLocation":null,"outcome":null,"possession":142,"xg":null}]