[{"teamId":941,"teamName":"Netherlands","players":[{"id":2988,"name":"Memphis Depay","jerseyNumber":10,"country":"Netherlands","position":"Center Forward"},{"id":3306,"name":"Nathan Aké","jerseyNumber":5,"country":"Netherlands","position":"Left Back"},{"id":3669,"name":"Virgil van Dijk","jerseyNumber":4,"country":"Netherlands","position":"Left Center Back"},{"id":7787,"name":"Stefan de Vrij","jerseyNumber":6,"country":"Netherlands","position":"Right Center Back"},{"id":7829,"name":"Wout Weghorst","jerseyNumber":9,"country":"Netherlands","position":"Center Forward"},{"id":8125,"name":"Denzel Dumfries","jerseyNumber":22,"country":"Netherlands","position":"Right Back"},{"id":15503,"name":"Jerdy Schouten","jerseyNumber":24,"country":"Netherlands","position":"Right Defensive Midfield"},{"id":15582,"name":"Donyell Malen","jerseyNumber":18,"country":"Netherlands","position":"Right Wing"},{"id":20750,"name":"Cody Mathès Gakpo","jerseyNumber":11,"country":"Netherlands","position":"Left Wing"},{"id":21582,"name":"Tijjani Reijnders","jerseyNumber":14,"country":"Netherlands","position":"Left Defensive Midfield"},{"id":21633,"name":"Joey Veerman","jerseyNumber":16,"country":"Netherlands","position":"Center Forward"},{"id":21880,"name":"Brian Brobbey","jerseyNumber":19,"country":"Netherlands","position":"Right Wing"},{"id":33281,"name":"Joshua Zirkzee","jerseyNumber":21,"country":"Netherlands","position":"Right Back"},{"id":37274,"name":"Bart Verbruggen","jerseyNumber":1,"country":"Netherlands","position":"Goalkeeper"},{"id":39167,"name":"Xavi Simons","jerseyNumber":7,"country":"Netherlands","position":"Center Attacking Midfield"}]},{"teamId":768,"teamName":"England","players":[{"id":3205,"name":"Kyle Walker","jerseyNumber":2,"country":"England","position":"Right Center Back"},{"id":3244,"name":"John Stones","jerseyNumber":5,"country":"England","position":"Center Back"},{"id":3308,"name":"Kieran Trippier","jerseyNumber":12,"country":"England","position":"Left Wing Back"},{"id":3382,"name":"Luke Shaw","jerseyNumber":3,"country":"England","position":"Left Wing Back"},{"id":3468,"name":"Jordan Pickford","jerseyNumber":1,"country":"England","position":"Goalkeeper"},{"id":3822,"name":"Ezri Konsa Ngoyo","jerseyNumber":14,"country":"England","position":"Right Wing Back"},{"id":3943,"name":"Declan Rice","jerseyNumber":4,"country":"England","position":"Left Defensive Midfield"},{"id":4354,"name":"Phil Foden","jerseyNumber":11,"country":"England","position":"Right Attacking Midfield"},{"id":4760,"name":"Ollie Watkins","jerseyNumber":19,"country":"England","position":"Center Forward"},{"id":10955,"name":"Harry Kane","jerseyNumber":9,"country":"England","position":"Center Forward"},{"id":22084,"name":"Bukayo Saka","jerseyNumber":7,"country":"England","position":"Right Wing Back"},{"id":29399,"name":"Conor Gallagher","jerseyNumber":16,"country":"England","position":"Right Defensive Midfield"},{"id":30714,"name":"Jude Bellingham","jerseyNumber":10,"country":"England","position":"Left Attacking Midfield"},{"id":34526,"name":"Marc Guehi","jerseyNumber":6,"country":"England","position":"Left Center Back"},{"id":39461,"name":"Cole Palmer","jerseyNumber":24,"country":"England","position":"Right Attacking Midfield"},{"id":99174,"name":"Kobbie Mainoo","jerseyNumber":26,"country":"England","position":"Right Defensive Midfield"}]}]