[{"id":"us_685345","index":0,"period":1,"minute":1,"second":0,"timestamp":"00:01:00.000","team":"Bayern Munich","player":"Harry Kane","type":"Shot","location":[90.72,42.96],"result":"Off T","outcome":"Off T","xg":0.0226,"bodyPart":"Right Foot","situation":"OpenPlay"},{"id":"us_685346","index":1,"period":1,"minute":9,"second":0,"timestamp":"00:09:00.000","team":"Bayern Munich","player":"Harry Kane","type":"Shot","location":[110.16,42.08],"result":"Goal","outcome":"Goal","xg":0.4402,"bodyPart":"Right Foot","situation":"OpenPlay"},{"id":"us_685347","index":2,"period":1,"minute":12,"second":0,"timestamp":"00:12:00.000","team":"Bayern Munich","player":"Harry Kane","type":"Shot","location":[97.44,41.2],"result":"Goal","outcome":"Goal","xg":0.1571,"bodyPart":"Right Foot","situation":"DirectFreekick"},{"id":"us_685348","index":19,"period":1,"minute":17,"second":0,"timestamp":"00:17:00.000","team":"FC Cologne","player":"Said El Mala","type":"Shot","location":[107.88,49.2],"result":"Goal","outcome":"Goal","xg":0.44,"bodyPart":"Left Foot","situation":"OpenPlay"},{"id":"us_685349","index":3,"period":1,"minute":21,"second":0,"timestamp":"00:21:00.000","team":"Bayern Munich","player":"Tom Bischof","type":"Shot","location":[97.56,44.08],"result":"Goal","outcome":"Goal","xg":0.0649,"bodyPart":"Left Foot","situation":"OpenPlay"},{"id":"us_685350","index":4,"period":1,"minute":25,"second":0,"timestamp":"00:25:00.000","team":"Bayern Munich","player":"Luis Díaz","type":"Shot","location":[102.24,56.56],"result":"Saved","outcome":"Saved","xg":0.0573,"bodyPart":"Right Foot","situation":"OpenPlay"},{"id":"us_685351","index":5,"period":1,"minute":26,"second":0,"timestamp":"00:26:00.000","team":"Bayern Munich","player":"Leon Goretzka","type":"Shot","location":[87,25.68],"result":"Blocked","outcome":"Blocked","xg":0.0217,"bodyPart":"Right Foot","situation":"OpenPlay"},{"id":"us_685352","index":6,"period":1,"minute":27,"second":0,"timestamp":"00:27:00.000","team":"Bayern Munich","player":"Lennart Karl","type":"Shot","location":[111.6,36.16],"result":"Off T","outcome":"Off T","xg":0.1474,"bodyPart":"Left Foot","situation":"OpenPlay"},{"id":"us_685353","index":7,"period":1,"minute":42,"second":0,"timestamp":"00:42:00.000","team":"Bayern Munich","player":"Luis Díaz","type":"Shot","location":[105.96,36.64],"result":"Saved","outcome":"Saved","xg":0.4954,"bodyPart":"Right Foot","situation":"OpenPlay"},{"id":"us_685354","index":8,"period":1,"minute":43,"second":0,"timestamp":"00:43:00.000","team":"Bayern Munich","player":"Jamal Musiala","type":"Shot","location":[110.04,50.4],"result":"Off T","outcome":"Off T","xg":0.2992,"bodyPart":"Left Foot","situation":"OpenPlay"},{"id":"us_685355","index":9,"period":1,"minute":43,"second":0,"timestamp":"00:43:00.000","team":"Bayern Munich","player":"Harry Kane","type":"Shot","location":[115.08,40.72],"result":"Blocked","outcome":"Blocked","xg":0.165,"bodyPart":"Right Foot","situation":"OpenPlay"},{"id":"us_685359","index":23,"period":2,"minute":46,"second":0,"timestamp":"00:46:00.000","team":"FC Cologne","player":"Linton Maina","type":"Shot","location":[104.28,21.84],"result":"Off T","outcome":"Off T","xg":0.0392,"bodyPart":"Left Foot","situation":"OpenPlay"},{"id":"us_685356","index":20,"period":2,"minute":48,"second":0,"timestamp":"00:48:00.000","team":"FC Cologne","player":"Jahmai Simpson-Pusey","type":"Shot","location":[105.24,43.44],"result":"Blocked","outcome":"Blocked","xg":0.0334,"bodyPart":"Left Foot","situation":"FromCorner"},{"id":"us_685357","index":21,"period":2,"minute":48,"second":0,"timestamp":"00:48:00.000","team":"FC Cologne","player":"Eric Martel","type":"Shot","location":[102.96,43.84],"result":"Blocked","outcome":"Blocked","xg":0.0547,"bodyPart":"Right Foot","situation":"FromCorner"},{"id":"us_685358","index":22,"period":2,"minute":48,"second":0,"timestamp":"00:48:00.000","team":"FC Cologne","player":"Jakub Kaminski","type":"Shot","location":[102.6,30.4],"result":"Blocked","outcome":"Blocked","xg":0.0414,"bodyPart":"Right Foot","situation":"FromCorner"},{"id":"us_685360","index":10,"period":2,"minute":52,"second":0,"timestamp":"00:52:00.000","team":"Bayern Munich","player":"Lennart Karl","type":"Shot","location":[101.16,32.72],"result":"Off T","outcome":"Off T","xg":0.0684,"bodyPart":"Left Foot","situation":"OpenPlay"},{"id":"us_685361","index":24,"period":2,"minute":58,"second":0,"timestamp":"00:58:00.000","team":"FC Cologne","player":"Marius Bülter","type":"Shot","location":[113.76,32.88],"result":"Off T","outcome":"Off T","xg":0.0764,"bodyPart":"Head","situation":"FromCorner"},{"id":"us_685362","index":11,"period":2,"minute":63,"second":0,"timestamp":"00:63:00.000","team":"Bayern Munich","player":"Jamal Musiala","type":"Shot","location":[98.88,40.08],"result":"Blocked","outcome":"Blocked","xg":0.0445,"bodyPart":"Right Foot","situation":"FromCorner"},{"id":"us_685363","index":12,"period":2,"minute":64,"second":0,"timestamp":"00:64:00.000","team":"Bayern Munich","player":"Luis Díaz","type":"Shot","location":[98.52,52.64],"result":"Off T","outcome":"Off T","xg":0.0421,"bodyPart":"Right Foot","situation":"FromCorner"},{"id":"us_685364","index":25,"period":2,"minute":66,"second":0,"timestamp":"00:66:00.000","team":"FC Cologne","player":"Sebastian Sebulonsen","type":"Shot","location":[103.56,29.68],"result":"Blocked","outcome":"Blocked","xg":0.0757,"bodyPart":"Right Foot","situation":"OpenPlay"},{"id":"us_685365","index":26,"period":2,"minute":66,"second":0,"timestamp":"00:66:00.000","team":"FC Cologne","player":"Eric Martel","type":"Shot","location":[111.48,43.44],"result":"Off T","outcome":"Off T","xg":0.1066,"bodyPart":"Head","situation":"FromCorner"},{"id":"us_685366","index":13,"period":2,"minute":68,"second":0,"timestamp":"00:68:00.000","team":"Bayern Munich","player":"Harry Kane","type":"Shot","location":[84.6,40],"result":"Goal","outcome":"Goal","xg":0.0198,"bodyPart":"Right Foot","situation":"OpenPlay"},{"id":"us_685367","index":14,"period":2,"minute":77,"second":0,"timestamp":"00:77:00.000","team":"Bayern Munich","player":"Leon Goretzka","type":"Shot","location":[90.12,51.92],"result":"Blocked","outcome":"Blocked","xg":0.0551,"bodyPart":"Right Foot","situation":"DirectFreekick"},{"id":"us_685368","index":15,"period":2,"minute":82,"second":0,"timestamp":"00:82:00.000","team":"Bayern Munich","player":"Nicolas Jackson","type":"Shot","location":[108.24,43.44],"result":"Goal","outcome":"Goal","xg":0.4381,"bodyPart":"Left Foot","situation":"OpenPlay"},{"id":"us_685369","index":16,"period":2,"minute":84,"second":0,"timestamp":"00:84:00.000","team":"Bayern Munich","player":"Joshua Kimmich","type":"Shot","location":[99.96,33.68],"result":"Off T","outcome":"Off T","xg":0.0633,"bodyPart":"Right Foot","situation":"OpenPlay"},{"id":"us_685370","index":27,"period":2,"minute":87,"second":0,"timestamp":"00:87:00.000","team":"FC Cologne","player":"Ísak Bergmann Jóhannesson","type":"Shot","location":[89.76,24.8],"result":"Saved","outcome":"Saved","xg":0.0127,"bodyPart":"Left Foot","situation":"OpenPlay"},{"id":"us_685371","index":17,"period":2,"minute":89,"second":0,"timestamp":"00:89:00.000","team":"Bayern Munich","player":"Raphael Guerreiro","type":"Shot","location":[107.28,51.68],"result":"Off T","outcome":"Off T","xg":0.0793,"bodyPart":"Left Foot","situation":"OpenPlay"},{"id":"us_685372","index":18,"period":2,"minute":91,"second":0,"timestamp":"00:91:00.000","team":"Bayern Munich","player":"Michael Olise","type":"Shot","location":[107.52,32.24],"result":"Blocked","outcome":"Blocked","xg":0.134,"bodyPart":"Right Foot","situation":"OpenPlay"}]