[{"teamId":771,"teamName":"France","players":[{"id":3009,"name":"Kylian Mbappé Lottin","jerseyNumber":10,"country":"France","position":"Left Wing"},{"id":3026,"name":"Adrien Rabiot","jerseyNumber":14,"country":"France","position":"Left Center Midfield"},{"id":3604,"name":"Olivier Giroud","jerseyNumber":9,"country":"France","position":"Right Wing"},{"id":3761,"name":"Mike Maignan","jerseyNumber":16,"country":"France","position":"Goalkeeper"},{"id":3961,"name":"N'Golo Kanté","jerseyNumber":13,"country":"France","position":"Right Center Midfield"},{"id":4445,"name":"Jules Koundé","jerseyNumber":5,"country":"France","position":"Right Back"},{"id":5477,"name":"Ousmane Dembélé","jerseyNumber":11,"country":"France","position":"Right Wing"},{"id":5487,"name":"Antoine Griezmann","jerseyNumber":7,"country":"France","position":"Right Center Midfield"},{"id":6704,"name":"Theo Bernard François Hernández","jerseyNumber":22,"country":"France","position":"Left Back"},{"id":8519,"name":"Dayotchanculle Upamecano","jerseyNumber":4,"country":"France","position":"Right Center Back"},{"id":10481,"name":"Aurélien Djani Tchouaméni","jerseyNumber":8,"country":"France","position":"Center Defensive Midfield"},{"id":17592,"name":"William Saliba","jerseyNumber":17,"country":"France","position":"Left Center Back"},{"id":22097,"name":"Randal Kolo Muani","jerseyNumber":12,"country":"France","position":"Center Forward"},{"id":24778,"name":"Eduardo Camavinga","jerseyNumber":6,"country":"France","position":"Left Center Midfield"},{"id":39420,"name":"Bradley Barcola","jerseyNumber":25,"country":"France","position":"Center Forward"}]},{"teamId":772,"teamName":"Spain","players":[{"id":3042,"name":"Mikel Merino Zazón","jerseyNumber":6,"country":"Spain","position":"Center Attacking Midfield"},{"id":3477,"name":"Álvaro Borja Morata Martín","jerseyNumber":7,"country":"Spain","position":"Center Forward"},{"id":4353,"name":"Aymeric Laporte","jerseyNumber":14,"country":"Spain","position":"Left Center Back"},{"id":5202,"name":"José Ignacio Fernández Iglesias","jerseyNumber":4,"country":"Spain","position":"Right Center Back"},{"id":6655,"name":"Fabián Ruiz Peña","jerseyNumber":8,"country":"Spain","position":"Left Defensive Midfield"},{"id":6685,"name":"Mikel Oyarzabal Ugarte","jerseyNumber":21,"country":"Spain","position":"Center Forward"},{"id":6748,"name":"Ferrán Torres García","jerseyNumber":11,"country":"Spain","position":"Right Wing"},{"id":6765,"name":"Rodrigo Hernández Cascante","jerseyNumber":16,"country":"Spain","position":"Right Defensive Midfield"},{"id":6821,"name":"Jesús Navas González","jerseyNumber":22,"country":"Spain","position":"Right Back"},{"id":11748,"name":"Unai Simón Mendibil","jerseyNumber":23,"country":"Spain","position":"Goalkeeper"},{"id":16532,"name":"Daniel Olmo Carvajal","jerseyNumber":10,"country":"Spain","position":"Center Attacking Midfield"},{"id":17620,"name":"Marc Cucurella Saseta","jerseyNumber":24,"country":"Spain","position":"Left Back"},{"id":24921,"name":"Martín Zubimendi Ibáñez","jerseyNumber":18,"country":"Spain","position":"Left Wing"},{"id":41542,"name":"Daniel Vivian Moreno","jerseyNumber":5,"country":"Spain","position":"Right Back"},{"id":68574,"name":"Nicholas Williams Arthuer","jerseyNumber":17,"country":"Spain","position":"Left Wing"},{"id":316046,"name":"Lamine Yamal Nasraoui Ebana","jerseyNumber":19,"country":"Spain","position":"Right Wing"}]}]